Workbook

Sheet 04.05.2026
A1: SALES ORDER REPORT | K1: =TODAY() -> 46171
A2: Date | B2: Delivery Date | C2: Job Number | D2: SO Number | E2: Customer Ref. | F2: Customer | G2: Total | H2: Sales Rep | I2: Status | J2: Payment Status | K2: Details | L2: Planned Delivery Date
A3: 46120 | B3: 46146.328 | C3: FM3985 | D3: SO4510 | E3: 62048 | F3: Chabo & Joubert Air Conditioning (Pty) Ltd | G3: 50593.1 | H3: Sizwe Tshabalala | I3: Ready-Dispatch | J3: ACCOUNT - UP TO DATE | K3: UV250/1/6 c/w 0.18kW 960rpm 6pole 220V Single Phase Motor incl Bird Screen (Qty: 2), UV400/3/6 c/w 0.55kW 960rpm 6Pole 380V Motor incl Bird Screen (Qty: 1) | L3: =B3 -> 46146.328
A4: 46133 | B4: 46146.328 | C4: FM4008 | D4: SO4537 | E4: PO-0070 | F4: Duty Point Pty Ltd | G4: 28418.48 | H4: Mashudu Tshifularo | I4: Ready-Dispatch | J4: CASH SALE – PARTIAL | K4: MAXFLO 800/150/10 A c/w 4,00KW 4P 380V - PLATE AXIAL (Qty: 2) | L4: =B4 -> 46146.328
A5: 46136 | B5: 46146.328 | C5: FM4017 | D5: SO4546 | E5: PO145956 | F5: Howden Power a Div of Howden Africa (Pty) LTD | G5: 15437.6 | H5: Sizwe Tshabalala | I5: Ready-Dispatch | J5: ACCOUNT - UP TO DATE | K5: SCL-K03 MS-0.55kW-380V (Qty: 1) | L5: =B5 -> 46146.328
A6: 46111 | B6: 46171 | C6: FM3967 | D6: SO4492 | E6: PO260306 | F6: Alpha Air Ventilation Services | G6: 9014.21 | H6: Sizwe Tshabalala | I6: On Hold | K6: MAJAX-2 500 c/w 0,55KW 4P 380V (Qty: 1), 500 Diam Counter Flange (Qty: 2) | L6: =B6 -> 46171
A7: 46112 | B7: 46146.328 | C7: FM3974 | D7: SO4502 | E7: 210719 | F7: Kenmare Moma Processing (Mauritius) Limited | G7: 103711 | H7: Sizwe Tshabalala | I7: In Progress | J7: ACCOUNT - UP TO DATE | K7: SCL-K10 MS-11kW - Item no 28000234 (Qty: 1) | L7: =B7 -> 46146.328
A8: 46112 | B8: 46146.328 | C8: FM3997 | D8: SO4525 | E8: 211035 | F8: Kenmare Moma Processing (Mauritius) Limited | G8: 83433 | H8: Sizwe Tshabalala | I8: In Progress | J8: ACCOUNT - UP TO DATE | K8: SCL-K08 MS-7.5kW (Qty: 1) | L8: =B8 -> 46146.328
A9: 46119 | B9: 46146.328 | C9: FM3979 | D9: SO4506 | E9: 14264 | F9: Arta Masjinerie | G9: 58613.2 | H9: Simon Mokgola | I9: In Progress | J9: ACCOUNT - UP TO DATE | K9: 800 c/w 3.0Kw 4Pole 380V (Qty: 4) | L9: =B9 -> 46146.328
A10: 46133 | B10: 46146.328 | C10: FM4020 | D10: SO4549 | E10: nan | F10: Sulit Projects | G10: 1573.2 | H10: Mashudu Tshifularo | I10: In Progress | J10: CASH SALE - PAID | K10: RAD 125 (Qty: 1) | L10: =B10 -> 46146.328
A11: 46136 | B11: 46146.328 | C11: FM4016 | D11: SO4545 | E11: cash sale | F11: ZEFS More Vision | G11: 57647.2 | H11: Mashudu Tshifularo | I11: In Progress | J11: CASH SALE - PAID | K11: MAXFLO 500/150/10 A c/w 1,10KW 4P 380V (Qty: 4), 500 Diam Mounting Feet (Qty: 12), MAXFLO 560/150/10 A c/w 1,10KW 4P 380V (Qty: 2), 560 Diam Mounting Feet (Qty: 6), 315 to 560 NDA RED ANeoprene Floor Mounts (Qty: 36) | L11: =B11 -> 46146.328
A12: 46111 | B12: 46171 | C12: FM3990 | D12: SO4517 | E12: PO:0000426 | F12: Compu Cool (Pty) Ltd | G12: 169353.6 | H12: Mashudu Tshifularo | I12: On Hold | K12: UV710/3/6 (Qty: 6) | L12: =B12 -> 46171
A13: 46069 | B13: 46157 | C13: FM3841 | D13: SO4372 | E13: PO2213 | F13: Hucra Fans | G13: 379993.35 | H13: Sales Agent Hucra Fans | I13: In Progress | J13: ACCOUNT - UP TO DATE | K13: SCL K11 MS - 11.0kW - 525V (Qty: 3) | L13: =B13 -> 46157
A14: 46077 | B14: 46157 | C14: FM3874 | D14: SO4404 | E14: PO2174 | F14: ITD North Pty Ltd | G14: 94247.1 | H14: Mashudu Tshifularo | I14: In Progress | J14: CASH SALE – PARTIAL | K14: RDH 710 K2 - Nicotra Fan (Qty: 1) | L14: =B14 -> 46157
F15: Total Value (All): | G15: =SUM(G3:G14) -> 1052035
F17: BREAKDOWN
F18: Cash Sale (May): | G18: =SUMIFS(G3:G14, J3:J14, "*CASH SALE*", L3:L14, ">="&EOMONTH(TODAY(),-1)+1, L3:L14, "<="&EOMONTH(TODAY(),0)) -> 181885.98 | I18: Cash Sale (June): | J18: =SUMIFS(G3:G14, J3:J14, "*CASH SALE*", L3:L14, ">="&EOMONTH(TODAY(),0)+1, L3:L14, "<="&EOMONTH(TODAY(),1)) -> 0
F19: Account (May): | G19: =SUMIFS(G3:G14, J3:J14, "*ACCOUNT*", L3:L14, ">="&EOMONTH(TODAY(),-1)+1, L3:L14, "<="&EOMONTH(TODAY(),0)) -> 691781.25 | I19: Account (June): | J19: =SUMIFS(G3:G14, J3:J14, "*ACCOUNT*", L3:L14, ">="&EOMONTH(TODAY(),0)+1, L3:L14, "<="&EOMONTH(TODAY(),1)) -> 0
A22: Date | B22: Delivery Date | C22: Job Number | D22: SO Number | E22: Customer Ref. | F22: Customer | G22: Total | H22: Sales Rep | I22: Status | J22: Payment Status | K22: Comments
A23: 46120 | B23: 46146.328 | C23: FM3985 | D23: SO4510 | E23: 62048 | F23: Chabo & Joubert Air Conditioning (Pty) Ltd | G23: 50593.1 | H23: Sizwe Tshabalala | I23: Ready-Dispatch | J23: ACCOUNT - UP TO DATE
A24: 46133 | B24: 46146.328 | C24: FM4008 | D24: SO4537 | E24: PO-0070 | F24: Duty Point Pty Ltd | G24: 28418.48 | H24: Mashudu Tshifularo | I24: Ready-Dispatch | J24: CASH SALE – PARTIAL | K24: Balance payment required prior to delivery/collection
A25: 46136 | B25: 46146.328 | C25: FM4017 | D25: SO4546 | E25: PO145956 | F25: Howden Power a Div of Howden Africa (Pty) LTD | G25: 15437.6 | H25: Sizwe Tshabalala | I25: Ready-Dispatch | J25: ACCOUNT - UP TO DATE | K25: Client to collect 28/04/2026 - Sizwe to advise
A26: 46111 | B26: 46171 | C26: FM3967 | D26: SO4492 | E26: PO260306 | F26: Alpha Air Ventilation Services | G26: 9014.21 | H26: Sizwe Tshabalala | I26: On Hold
A27: 46112 | B27: 46146.328 | C27: FM3974 | D27: SO4502 | E27: 210719 | F27: Kenmare Moma Processing (Mauritius) Limited | G27: 103711 | H27: Sizwe Tshabalala | I27: In Progress | J27: ACCOUNT - UP TO DATE
A28: 46112 | B28: 46146.328 | C28: FM3997 | D28: SO4525 | E28: 211035 | F28: Kenmare Moma Processing (Mauritius) Limited | G28: 83433 | H28: Sizwe Tshabalala | I28: In Progress | J28: ACCOUNT - UP TO DATE
A29: 46119 | B29: 46146.328 | C29: FM3979 | D29: SO4506 | E29: 14264 | F29: Arta Masjinerie | G29: 58613.2 | H29: Simon Mokgola | I29: In Progress | J29: ACCOUNT - UP TO DATE
A30: 46133 | B30: 46146.328 | C30: FM4020 | D30: SO4549 | E30: nan | F30: Sulit Projects | G30: 1573.2 | H30: Mashudu Tshifularo | I30: In Progress | J30: CASH SALE - PAID
A31: 46136 | B31: 46146.328 | C31: FM4016 | D31: SO4545 | E31: cash sale | F31: ZEFS More Vision | G31: 57647.2 | H31: Mashudu Tshifularo | I31: In Progress | J31: CASH SALE - PAID
F32: Due Today - Total: | G32: =SUM(G23:G31) -> 408440.99
F34: Ready-Dispatch: | G34: =SUMIFS(G3:G14, I3:I14, "*Ready*Dispatch*") -> 94449.18
A37: Recommended Print Range: A1:L39
A38: Suggested Date for Next Update: 05.05.2026

Sheet 05.05.2026
A1: SALES ORDER REPORT | K1: =TODAY() -> 46171
A2: Date | B2: Delivery Date | C2: Job Number | D2: SO Number | E2: Customer Ref. | F2: Customer | G2: Total | H2: Sales Rep | I2: Status | J2: Payment Status | K2: Details | L2: Planned Delivery Date
A3: 46120 | B3: 46147.402 | C3: FM3985 | D3: SO4510 | E3: 62048 | F3: Chabo & Joubert Air Conditioning (Pty) Ltd | G3: 50593.1 | H3: Sizwe Tshabalala | I3: Ready-Dispatch | J3: ACCOUNT - UP TO DATE | K3: UV250/1/6 c/w 0.18kW 960rpm 6pole 220V Single Phase Motor incl Bird Screen (Qty: 2), UV400/3/6 c/w 0.55kW 960rpm 6Pole 380V Motor incl Bird Screen (Qty: 1) | L3: =B3 -> 46147.402
A4: 46136 | B4: 46147.402 | C4: FM4017 | D4: SO4546 | E4: PO145956 | F4: Howden Power a Div of Howden Africa (Pty) LTD | G4: 15437.6 | H4: Sizwe Tshabalala | I4: Ready-Dispatch | J4: ACCOUNT - UP TO DATE | K4: SCL-K03 MS-0.55kW-380V (Qty: 1) | L4: =B4 -> 46147.402
A5: 46133 | B5: 46147.402 | C5: FM4020 | D5: SO4549 | E5: nan | F5: Sulit Projects | G5: 1573.2 | H5: Mashudu Tshifularo | I5: Ready-Dispatch | J5: CASH SALE - PAID | K5: RAD 125 (Qty: 1) | L5: =B5 -> 46147.402
A6: 46146 | B6: 46149 | C6: FM4025 | D6: SO4559 | E6: PO0000475 | F6: Compu Cool (Pty) Ltd | G6: 11429.61 | H6: Mashudu Tshifularo | I6: In Progress | J6: ACCOUNT - UP TO DATE | K6: MAXFLO 710/150/10 A c/w 2,20KW 4P 380V (Qty: 1) | L6: =B6 -> 46149
A7: 46111 | B7: 46171 | C7: FM3990 | D7: SO4517 | E7: PO:0000426 | F7: Compu Cool (Pty) Ltd | G7: 169353.6 | H7: Mashudu Tshifularo | I7: On Hold | J7: ACCOUNT - UP TO DATE | K7: UV710/3/6 (Qty: 6) | L7: =B7 -> 46171
A8: 46112 | B8: 46150 | C8: FM3974 | D8: SO4502 | E8: 210719 | F8: Kenmare Moma Processing (Mauritius) Limited | G8: 103711 | H8: Sizwe Tshabalala | I8: In Progress | J8: ACCOUNT - UP TO DATE | K8: SCL-K10 MS-11kW - Item no 28000234 (Qty: 1) | L8: =B8 -> 46150
A9: 46112 | B9: 46150 | C9: FM3997 | D9: SO4525 | E9: 211035 | F9: Kenmare Moma Processing (Mauritius) Limited | G9: 83433 | H9: Sizwe Tshabalala | I9: In Progress | J9: ACCOUNT - UP TO DATE | K9: SCL-K08 MS-7.5kW (Qty: 1) | L9: =B9 -> 46150
A10: 46069 | B10: 46157 | C10: FM3841 | D10: SO4372 | E10: PO2213 | F10: Hucra Fans | G10: 379993.35 | H10: Sales Agent Hucra Fans | I10: In Progress | J10: ACCOUNT - UP TO DATE | K10: SCL K11 MS - 11.0kW - 525V (Qty: 3) | L10: =B10 -> 46157
A11: 46077 | B11: 46157 | C11: FM3874 | D11: SO4404 | E11: PO2174 | F11: ITD North Pty Ltd | G11: 94247.1 | H11: Mashudu Tshifularo | I11: In Progress | J11: CASH SALE – PARTIAL | K11: RDH 710 K2 - Nicotra Fan (Qty: 1) | L11: =B11 -> 46157
A12: 46111 | B12: 46171 | C12: FM3967 | D12: SO4492 | E12: PO260306 | F12: Alpha Air Ventilation Services | G12: 9014.21 | H12: Sizwe Tshabalala | I12: On Hold | J12: =IFERROR(VLOOKUP(D12, '04.05.2026'!D:J, 7, FALSE), "") -> 0 | K12: MAJAX-2 500 c/w 0,55KW 4P 380V (Qty: 1), 500 Diam Counter Flange (Qty: 2) | L12: =B12 -> 46171
A13: 46057 | B13: 46171 | C13: Pending | D13: SO4558 | E13: FMTA4398-Thabakgolo | F13: Oribi Air CC | G13: 427841.4 | H13: Mashudu Tshifularo | I13: Pending | J13: =IFERROR(VLOOKUP(D13, '04.05.2026'!D:J, 7, FALSE), "") | K13: LINEO 250 QUIET-5.1.1 (Qty: 24), LINEO 315 QUIET-5.6.1 (Qty: 12) | L13: =B13 -> 46171
A14: 46128 | B14: 46171 | C14: Pending | D14: SO4554 | E14: FMTA4599 | F14: Matla Solution Group | G14: 82900.05 | H14: Mashudu Tshifularo | I14: Pending | J14: =IFERROR(VLOOKUP(D14, '04.05.2026'!D:J, 7, FALSE), "") | K14: LINEO 315 QUIET - EF 1 (Qty: 1), LINEO 250 QUIET - EF 2 (Qty: 1), LINEO 200 QUIET - EF 3 (Qty: 1), KDAXIS 200 - EF 4 (Qty: 1), KDAXIS 200 - EF 5 (Qty: 1), MAXFLO 630/250/14 A c/w 1,10KW 4P 380V - FA 1 (Qty: 1), 630 Diam Silencer 1.5D Podded (Qty: 2), 630 Diam Counter Flange (Qty: 2), 630 Diam Mounting Feet (Qty: 4), 630 to 1000 NDB GREEN Neoprene Floor Mounts (Qty: 8), MAXFLO 710/250/14 A c/w 1,10KW 4P 380V - FA 2 (Qty: 1), 710 Diam Silencer 1.5D Podded (Qty: 2), 710 Diam Counter Flange (Qty: 2), 710 Diam Mounting Feet (Qty: 4), 630 to 1000 NDB GREEN Neoprene Floor Mounts (Qty: 8) | L14: =B14 -> 46171
A15: 46142 | B15: 46171 | C15: Pending | D15: SO4552 | E15: nan | F15: Neobionomics Services Pty Ltd | G15: 13711.09 | H15: Sizwe Tshabalala | I15: Pending | J15: =IFERROR(VLOOKUP(D15, '04.05.2026'!D:J, 7, FALSE), "") | K15: MAJAX-2 630 c/w 0,75KW 4P 380V (Qty: 1) | L15: =B15 -> 46171
A16: 46142 | B16: 46171 | C16: Pending | D16: SO4556 | E16: Constitutional Hill | F16: LJ Trading & Projects (Pty) Ltd | G16: 554227.55 | H16: Simon Mokgola | I16: Pending | J16: =IFERROR(VLOOKUP(D16, '04.05.2026'!D:J, 7, FALSE), "") | K16: Constitutional Hill (Qty: 1) | L16: =B16 -> 46171
A17: 46142 | B17: 46171 | C17: Pending | D17: SO4557 | E17: nan | F17: Vigeta Pty Ltd | G17: 204447 | H17: Simon Mokgola | I17: Pending | J17: =IFERROR(VLOOKUP(D17, '04.05.2026'!D:J, 7, FALSE), "") | K17: 630 Diam Vertical Discharge BASE c/w 2.2kW 4P 380V (Qty: 10) | L17: =B17 -> 46171
A18: 46142 | B18: 46171 | C18: Pending | D18: SO4553 | E18: FMTA4519 | F18: ST AIR SERVICES AND MAINTENANCE (PTY) LTD | G18: 426010.6 | H18: Simon Mokgola | I18: Pending | J18: =IFERROR(VLOOKUP(D18, '04.05.2026'!D:J, 7, FALSE), "") | K18: Mimosa Mall Office Park (Qty: 1) | L18: =B18 -> 46171
F19: Total Value (All): | G19: =SUM(G3:G18) -> 2627923.5
F21: BREAKDOWN
F22: Cash Sale (May): | G22: =SUMIFS(G3:G18, J3:J18, "*CASH SALE*", L3:L18, ">="&EOMONTH(TODAY(),-1)+1, L3:L18, "<="&EOMONTH(TODAY(),0)) -> 95820.3 | I22: Cash Sale (June): | J22: =SUMIFS(G3:G18, J3:J18, "*CASH SALE*", L3:L18, ">="&EOMONTH(TODAY(),0)+1, L3:L18, "<="&EOMONTH(TODAY(),1)) -> 0
F23: Account (May): | G23: =SUMIFS(G3:G18, J3:J18, "*ACCOUNT*", L3:L18, ">="&EOMONTH(TODAY(),-1)+1, L3:L18, "<="&EOMONTH(TODAY(),0)) -> 813951.26 | I23: Account (June): | J23: =SUMIFS(G3:G18, J3:J18, "*ACCOUNT*", L3:L18, ">="&EOMONTH(TODAY(),0)+1, L3:L18, "<="&EOMONTH(TODAY(),1)) -> 0
A26: Date | B26: Delivery Date | C26: Job Number | D26: SO Number | E26: Customer Ref. | F26: Customer | G26: Total | H26: Sales Rep | I26: Status | J26: Payment Status | K26: Comments
A27: 46120 | B27: 46147.402 | C27: FM3985 | D27: SO4510 | E27: 62048 | F27: Chabo & Joubert Air Conditioning (Pty) Ltd | G27: 50593.1 | H27: Sizwe Tshabalala | I27: Ready-Dispatch | J27: ACCOUNT - UP TO DATE | K27: Ready for collection 30/04/2026 - ST to advise
A28: 46133 | B28: 46147.402 | C28: FM4020 | D28: SO4549 | E28: nan | F28: Sulit Projects | G28: 1573.2 | H28: Mashudu Tshifularo | I28: Ready-Dispatch | J28: CASH SALE - PAID | K28: Invoiced - Ready for collection 04/05/2026 - MT to Advise
A29: 46136 | B29: 46147.402 | C29: FM4017 | D29: SO4546 | E29: PO145956 | F29: Howden Power a Div of Howden Africa (Pty) LTD | G29: 15437.6 | H29: Sizwe Tshabalala | I29: Ready-Dispatch | J29: ACCOUNT - UP TO DATE | K29: Client to collect 28/04/2026 - ST to advise
F30: Due Today - Total: | G30: =SUM(G27:G29) -> 67603.9
F32: Ready-Dispatch: | G32: =SUMIFS(G3:G18, I3:I18, "*Ready*Dispatch*") -> 67603.9

Sheet 06.05.2026
A1: SALES ORDER REPORT | K1: =TODAY() -> 46171
A2: Date | B2: Delivery Date | C2: Job Number | D2: SO Number | E2: Customer Ref. | F2: Customer | G2: Total | H2: Sales Rep | I2: Status | J2: Payment Status | K2: Details | L2: Planned Delivery Date
A3: 46136 | B3: 46148.4 | C3: FM4017 | D3: SO4546 | E3: PO145956 | F3: Howden Power a Div of Howden Africa (Pty) LTD | G3: 15437.6 | H3: Sizwe Tshabalala | I3: Ready-Dispatch | J3: ACCOUNT - UP TO DATE | K3: SCL-K03 MS-0.55kW-380V (Qty: 1) | L3: =B3 -> 46148.4
A4: 46146 | B4: 46149 | C4: FM4025 | D4: SO4559 | E4: PO0000475 | F4: Compu Cool (Pty) Ltd | G4: 11429.61 | H4: Mashudu Tshifularo | I4: In Progress | J4: ACCOUNT - UP TO DATE | K4: MAXFLO 710/150/10 A c/w 2,20KW 4P 380V (Qty: 1) | L4: =B4 -> 46149
A5: 46069 | B5: 46170 | C5: FM3841 | D5: SO4372 | E5: PO2213 | F5: Hucra Fans | G5: 379993.35 | H5: Sales Agent Hucra Fans | I5: In Progress | J5: ACCOUNT - UP TO DATE | K5: SCL K11 MS - 11.0kW - 525V (Qty: 3) | L5: =B5 -> 46170
A6: 46077 | B6: 46170 | C6: FM3874 | D6: SO4404 | E6: PO2174 | F6: ITD North Pty Ltd | G6: 94247.1 | H6: Mashudu Tshifularo | I6: In Progress | J6: CASH SALE – PARTIAL | K6: RDH 710 K2 - Nicotra Fan (Qty: 1) | L6: =B6 -> 46170
A7: 46057 | B7: 46171 | C7: Pending | D7: SO4558 | E7: FMTA4398-Thabakgolo | F7: Oribi Air CC | G7: 427841.4 | H7: Mashudu Tshifularo | I7: Pending | J7: =IFERROR(VLOOKUP(D7, '05.05.2026'!D:J, 7, FALSE), "") | K7: LINEO 250 QUIET-5.1.1 (Qty: 24), LINEO 315 QUIET-5.6.1 (Qty: 12) | L7: =B7 -> 46171
A8: 46111 | B8: 46171 | C8: FM3967 | D8: SO4492 | E8: PO260306 | F8: Alpha Air Ventilation Services | G8: 9014.21 | H8: Sizwe Tshabalala | I8: On Hold | J8: =IFERROR(VLOOKUP(D8, '05.05.2026'!D:J, 7, FALSE), "") -> 0 | K8: MAJAX-2 500 c/w 0,55KW 4P 380V (Qty: 1), 500 Diam Counter Flange (Qty: 2) | L8: =B8 -> 46171
A9: 46111 | B9: 46171 | C9: FM3990 | D9: SO4517 | E9: PO:0000426 | F9: Compu Cool (Pty) Ltd | G9: 169353.6 | H9: Mashudu Tshifularo | I9: On Hold | J9: =IFERROR(VLOOKUP(D9, '05.05.2026'!D:J, 7, FALSE), "") -> ACCOUNT - UP TO DATE | K9: UV710/3/6 (Qty: 6) | L9: =B9 -> 46171
A10: 46128 | B10: 46171 | C10: Pending | D10: SO4554 | E10: FMTA4599 | F10: Matla Solution Group | G10: 82900.05 | H10: Mashudu Tshifularo | I10: Pending | J10: =IFERROR(VLOOKUP(D10, '05.05.2026'!D:J, 7, FALSE), "") | K10: LINEO 315 QUIET - EF 1 (Qty: 1), LINEO 250 QUIET - EF 2 (Qty: 1), LINEO 200 QUIET - EF 3 (Qty: 1), KDAXIS 200 - EF 4 (Qty: 1), KDAXIS 200 - EF 5 (Qty: 1), MAXFLO 630/250/14 A c/w 1,10KW 4P 380V - FA 1 (Qty: 1), 630 Diam Silencer 1.5D Podded (Qty: 2), 630 Diam Counter Flange (Qty: 2), 630 Diam Mounting Feet (Qty: 4), 630 to 1000 NDB GREEN Neoprene Floor Mounts (Qty: 8), MAXFLO 710/250/14 A c/w 1,10KW 4P 380V - FA 2 (Qty: 1), 710 Diam Silencer 1.5D Podded (Qty: 2), 710 Diam Counter Flange (Qty: 2), 710 Diam Mounting Feet (Qty: 4), 630 to 1000 NDB GREEN Neoprene Floor Mounts (Qty: 8) | L10: =B10 -> 46171
A11: 46142 | B11: 46171 | C11: Pending | D11: SO4552 | E11: nan | F11: Neobionomics Services Pty Ltd | G11: 13711.09 | H11: Sizwe Tshabalala | I11: Pending | J11: =IFERROR(VLOOKUP(D11, '05.05.2026'!D:J, 7, FALSE), "") | K11: MAJAX-2 630 c/w 0,75KW 4P 380V (Qty: 1) | L11: =B11 -> 46171
A12: 46142 | B12: 46171 | C12: Pending | D12: SO4556 | E12: Constitutional Hill | F12: LJ Trading & Projects (Pty) Ltd | G12: 554227.55 | H12: Simon Mokgola | I12: Pending | J12: =IFERROR(VLOOKUP(D12, '05.05.2026'!D:J, 7, FALSE), "") | K12: Constitutional Hill (Qty: 1) | L12: =B12 -> 46171
A13: 46142 | B13: 46171 | C13: Pending | D13: SO4557 | E13: nan | F13: Vigeta Pty Ltd | G13: 204447 | H13: Simon Mokgola | I13: Pending | J13: =IFERROR(VLOOKUP(D13, '05.05.2026'!D:J, 7, FALSE), "") | K13: 630 Diam Vertical Discharge BASE c/w 2.2kW 4P 380V (Qty: 10) | L13: =B13 -> 46171
A14: 46142 | B14: 46171 | C14: Pending | D14: SO4553 | E14: FMTA4519 | F14: ST AIR SERVICES AND MAINTENANCE (PTY) LTD | G14: 426010.6 | H14: Simon Mokgola | I14: Pending | J14: =IFERROR(VLOOKUP(D14, '05.05.2026'!D:J, 7, FALSE), "") | K14: Mimosa Mall Office Park (Qty: 1) | L14: =B14 -> 46171
A15: 46112 | B15: 46293 | C15: FM3974 | D15: SO4502 | E15: 210719 | F15: Kenmare Moma Processing (Mauritius) Limited | G15: 103711 | H15: Sizwe Tshabalala | I15: In Progress | J15: ACCOUNT - UP TO DATE | K15: SCL-K10 MS-11kW - Item no 28000234 (Qty: 1) | L15: =B15 -> 46293
A16: 46112 | B16: 46293 | C16: FM3997 | D16: SO4525 | E16: 211035 | F16: Kenmare Moma Processing (Mauritius) Limited | G16: 83433 | H16: Sizwe Tshabalala | I16: In Progress | J16: ACCOUNT - UP TO DATE | K16: SCL-K08 MS-7.5kW (Qty: 1) | L16: =B16 -> 46293
F17: Total Value (All): | G17: =SUM(G3:G16) -> 2575757.2
F19: BREAKDOWN
F20: Cash Sale (May): | G20: =SUMIFS(G3:G16, J3:J16, "*CASH SALE*", L3:L16, ">="&EOMONTH(TODAY(),-1)+1, L3:L16, "<="&EOMONTH(TODAY(),0)) -> 94247.1 | I20: Cash Sale (June): | J20: =SUMIFS(G3:G16, J3:J16, "*CASH SALE*", L3:L16, ">="&EOMONTH(TODAY(),0)+1, L3:L16, "<="&EOMONTH(TODAY(),1)) -> 0
F21: Account (May): | G21: =SUMIFS(G3:G16, J3:J16, "*ACCOUNT*", L3:L16, ">="&EOMONTH(TODAY(),-1)+1, L3:L16, "<="&EOMONTH(TODAY(),0)) -> 576214.16 | I21: Account (June): | J21: =SUMIFS(G3:G16, J3:J16, "*ACCOUNT*", L3:L16, ">="&EOMONTH(TODAY(),0)+1, L3:L16, "<="&EOMONTH(TODAY(),1)) -> 0
A24: Date | B24: Delivery Date | C24: Job Number | D24: SO Number | E24: Customer Ref. | F24: Customer | G24: Total | H24: Sales Rep | I24: Status | J24: Payment Status | K24: Comments
A25: 46136 | B25: 46148.4 | C25: FM4017 | D25: SO4546 | E25: PO145956 | F25: Howden Power a Div of Howden Africa (Pty) LTD | G25: 15437.6 | H25: Sizwe Tshabalala | I25: Ready-Dispatch | J25: ACCOUNT - UP TO DATE | K25: Client to collect 28/04/2026 - ST to advise
F26: Due Today - Total: | G26: =SUM(G25:G25) -> 15437.6
F28: Ready-Dispatch: | G28: =SUMIFS(G3:G16, I3:I16, "*Ready*Dispatch*") -> 15437.6

Sheet 07.05.2026
A1: SALES ORDER REPORT | K1: =TODAY() -> 46171
A2: Date | B2: Delivery Date | C2: Job Number | D2: SO Number | E2: Customer Ref. | F2: Customer | G2: Total | H2: Sales Rep | I2: Status | J2: Payment Status | K2: Details | L2: Planned Delivery Date
A3: 46136 | B3: 46149.522 | C3: FM4017 | D3: SO4546 | E3: PO145956 | F3: Howden Power a Div of Howden Africa (Pty) LTD | G3: 15437.6 | H3: Sizwe Tshabalala | I3: In Progress | J3: ACCOUNT - UP TO DATE | K3: SCL-K03 MS-0.55kW-380V (Qty: 1) | L3: =B3 -> 46149.522
A4: 46142 | B4: 46171 | C4: Pending | D4: SO4556 | E4: Constitutional Hill | F4: LJ Trading & Projects (Pty) Ltd | G4: 554227.55 | H4: Simon Mokgola | I4: Pending | K4: Constitutional Hill (Qty: 1) | L4: =B4 -> 46171
A5: 46142 | B5: 46149.522 | C5: FM4031 | D5: SO4565 | E5: POAM26058144 | F5: Allbro Industries (PTY) Ltd | G5: 19154.4 | H5: Sizwe Tshabalala | I5: In Progress | J5: CASH SALE - PAID | K5: HV 7 c/w 0.45kw 6P 380v (Qty: 2), WEATHER LOUVRE 800(W)*800(H) HS NA (Qty: 2) | L5: =B5 -> 46149.522
A6: 46146 | B6: 46149.522 | C6: FM4025 | D6: SO4559 | E6: PO0000475 | F6: Compu Cool (Pty) Ltd | G6: 11429.61 | H6: Mashudu Tshifularo | I6: In Progress | J6: ACCOUNT - UP TO DATE | K6: MAXFLO 710/150/10 A c/w 2,20KW 4P 380V (Qty: 1) | L6: =B6 -> 46149.522
A7: 46148 | B7: 46157 | C7: FM4032 | D7: SO4566 | E7: FMTA4618 | F7: Breezeair Technical Services | G7: 13174.4 | H7: Mashudu Tshifularo | I7: In Progress | J7: CASH SALE - PAID | K7: MAXFLO 560/250/14 A c/w 1,10KW 4P 380V (Qty: 1), 560 Diam Counter Flange (Qty: 2), 560 Diam Mounting Feet (Qty: 4), 315 to 560 NDA RED ANeoprene Floor Mounts (Qty: 8) | L7: =B7 -> 46157
A8: 46077 | B8: 46169 | C8: FM3874 | D8: SO4404 | E8: PO2174 | F8: ITD North Pty Ltd | G8: 94247.1 | H8: Mashudu Tshifularo | I8: In Progress | J8: CASH SALE – PARTIAL | K8: RDH 710 K2 - Nicotra Fan (Qty: 1) | L8: =B8 -> 46169
A9: 46069 | B9: 46170 | C9: FM3841 | D9: SO4372 | E9: PO2213 | F9: Hucra Fans | G9: 379993.35 | H9: Sales Agent Hucra Fans | I9: In Progress | J9: ACCOUNT - UP TO DATE | K9: SCL K11 MS - 11.0kW - 525V (Qty: 3) | L9: =B9 -> 46170
A10: 46112 | B10: 46170 | C10: FM3974 | D10: SO4502 | E10: 210719 | F10: Kenmare Moma Processing (Mauritius) Limited | G10: 103711 | H10: Sizwe Tshabalala | I10: In Progress | J10: ACCOUNT - UP TO DATE | K10: SCL-K10 MS-11kW - Item no 28000234 (Qty: 1) | L10: =B10 -> 46170
A11: 46112 | B11: 46170 | C11: FM3997 | D11: SO4525 | E11: 211035 | F11: Kenmare Moma Processing (Mauritius) Limited | G11: 83433 | H11: Sizwe Tshabalala | I11: In Progress | J11: ACCOUNT - UP TO DATE | K11: SCL-K08 MS-7.5kW (Qty: 1) | L11: =B11 -> 46170
A12: 46057 | B12: 46171 | C12: Pending | D12: SO4558 | E12: FMTA4398-Thabakgolo | F12: Oribi Air CC | G12: 427841.4 | H12: Mashudu Tshifularo | I12: Pending | K12: LINEO 250 QUIET-5.1.1 (Qty: 24), LINEO 315 QUIET-5.6.1 (Qty: 12) | L12: =B12 -> 46171
A13: 46111 | B13: 46171 | C13: FM3967 | D13: SO4492 | E13: PO260306 | F13: Alpha Air Ventilation Services | G13: 9014.21 | H13: Sizwe Tshabalala | I13: Pending | K13: MAJAX-2 500 c/w 0,55KW 4P 380V (Qty: 1), 500 Diam Counter Flange (Qty: 2) | L13: =B13 -> 46171
A14: 46111 | B14: 46171 | C14: FM3990 | D14: SO4517 | E14: PO:0000426 | F14: Compu Cool (Pty) Ltd | G14: 169353.6 | H14: Mashudu Tshifularo | I14: Pending | K14: UV710/3/6 (Qty: 6) | L14: =B14 -> 46171
A15: 46128 | B15: 46171 | C15: Pending | D15: SO4554 | E15: FMTA4599 | F15: Matla Solution Group | G15: 82900.05 | H15: Mashudu Tshifularo | I15: Pending | K15: LINEO 315 QUIET - EF 1 (Qty: 1), LINEO 250 QUIET - EF 2 (Qty: 1), LINEO 200 QUIET - EF 3 (Qty: 1), KDAXIS 200 - EF 4 (Qty: 1), KDAXIS 200 - EF 5 (Qty: 1), MAXFLO 630/250/14 A c/w 1,10KW 4P 380V - FA 1 (Qty: 1), 630 Diam Silencer 1.5D Podded (Qty: 2), 630 Diam Counter Flange (Qty: 2), 630 Diam Mounting Feet (Qty: 4), 630 to 1000 NDB GREEN Neoprene Floor Mounts (Qty: 8), MAXFLO 710/250/14 A c/w 1,10KW 4P 380V - FA 2 (Qty: 1), 710 Diam Silencer 1.5D Podded (Qty: 2), 710 Diam Counter Flange (Qty: 2), 710 Diam Mounting Feet (Qty: 4), 630 to 1000 NDB GREEN Neoprene Floor Mounts (Qty: 8) | L15: =B15 -> 46171
A16: 46142 | B16: 46171 | C16: Pending | D16: SO4552 | E16: nan | F16: Neobionomics Services Pty Ltd | G16: 13711.09 | H16: Sizwe Tshabalala | I16: Pending | K16: MAJAX-2 630 c/w 0,75KW 4P 380V (Qty: 1) | L16: =B16 -> 46171
A17: 46142 | B17: 46171 | C17: Pending | D17: SO4553 | E17: FMTA4519 | F17: ST AIR SERVICES AND MAINTENANCE (PTY) LTD | G17: 426010.6 | H17: Simon Mokgola | I17: Pending | K17: Mimosa Mall Office Park (Qty: 1) | L17: =B17 -> 46171
A18: 46142 | B18: 46171 | C18: FM4036 | D18: SO4555 | E18: FM4035-FM4036 | F18: Michmat Projects | G18: 310411 | H18: Mashudu - R.O.A | I18: Pending | K18: MFAJAX-3 1250 c/w 45,00KW 4P 380V (Qty: 3), 1250 Diam Counter Flange (Qty: 6), 1250 Diam Mounting Feet (Qty: 6), 630 to 1000 NDB GREEN Neoprene Floor Mounts (Qty: 12), MAJAX-3 560 c/w 5,50KW 2P 380V (Qty: 2), 560 Diam Counter Flange (Qty: 4), 560 Diam Mounting Feet (Qty: 4), 315 to 560 NDA RED ANeoprene Floor Mounts (Qty: 8) | L18: =B18 -> 46171
A19: 46142 | B19: 46171 | C19: Pending | D19: SO4557 | E19: nan | F19: Vigeta Pty Ltd | G19: 204447 | H19: Simon Mokgola | I19: Pending | K19: 630 Diam Vertical Discharge BASE c/w 2.2kW 4P 380V (Qty: 10) | L19: =B19 -> 46171
F20: Total Value (All): | G20: =SUM(G3:G19) -> 2918497
F22: BREAKDOWN
F23: Cash Sale (May): | G23: =SUMIFS(G3:G19, J3:J19, "*CASH SALE*", L3:L19, ">="&EOMONTH(TODAY(),-1)+1, L3:L19, "<="&EOMONTH(TODAY(),0)) -> 126575.9 | I23: Cash Sale (June): | J23: =SUMIFS(G3:G19, J3:J19, "*CASH SALE*", L3:L19, ">="&EOMONTH(TODAY(),0)+1, L3:L19, "<="&EOMONTH(TODAY(),1)) -> 0
F24: Account (May): | G24: =SUMIFS(G3:G19, J3:J19, "*ACCOUNT*", L3:L19, ">="&EOMONTH(TODAY(),-1)+1, L3:L19, "<="&EOMONTH(TODAY(),0)) -> 594004.56 | I24: Account (June): | J24: =SUMIFS(G3:G19, J3:J19, "*ACCOUNT*", L3:L19, ">="&EOMONTH(TODAY(),0)+1, L3:L19, "<="&EOMONTH(TODAY(),1)) -> 0
A27: Date | B27: Delivery Date | C27: Job Number | D27: SO Number | E27: Customer Ref. | F27: Customer | G27: Total | H27: Sales Rep | I27: Status | J27: Payment Status | K27: Comments
A28: 46136 | B28: 46149.522 | C28: FM4017 | D28: SO4546 | E28: PO145956 | F28: Howden Power a Div of Howden Africa (Pty) LTD | G28: 15437.6 | H28: Sizwe Tshabalala | I28: In Progress | J28: ACCOUNT - UP TO DATE
A29: 46142 | B29: 46171 | C29: Pending | D29: SO4556 | E29: Constitutional Hill | F29: LJ Trading & Projects (Pty) Ltd | G29: 554227.55 | H29: Simon Mokgola | I29: Pending
A30: 46142 | B30: 46149.522 | C30: FM4031 | D30: SO4565 | E30: POAM26058144 | F30: Allbro Industries (PTY) Ltd | G30: 19154.4 | H30: Sizwe Tshabalala | I30: In Progress | J30: CASH SALE - PAID
A31: 46146 | B31: 46149.522 | C31: FM4025 | D31: SO4559 | E31: PO0000475 | F31: Compu Cool (Pty) Ltd | G31: 11429.61 | H31: Mashudu Tshifularo | I31: In Progress | J31: ACCOUNT - UP TO DATE
F32: Due Today - Total: | G32: =SUM(G28:G31) -> 600249.16
F34: Ready-Dispatch: | G34: =SUMIFS(G3:G19, I3:I19, "*Ready*Dispatch*") -> 0
A37: Recommended Print Range: A1:L39
A38: Suggested Date for Next Update: 08.05.2026

Sheet 08.05.2026
A1: SALES ORDER REPORT | K1: =TODAY() -> 46171
A2: Date | B2: Delivery Date | C2: Job Number | D2: SO Number | E2: Customer Ref. | F2: Customer | G2: Total | H2: Sales Rep | I2: Status | J2: Payment Status | K2: Details | L2: Planned Delivery Date
A3: 46142 | B3: 46155 | C3: FM4031 | D3: SO4565 | E3: POAM26058144 | F3: Allbro Industries (PTY) Ltd | G3: 19154.4 | H3: Sizwe Tshabalala | I3: In Progress | J3: CASH SALE - PAID | K3: HV 7 c/w 0.45kw 6P 380v (Qty: 2), WEATHER LOUVRE 800(W)*800(H) HS NA (Qty: 2) | L3: =B3 -> 46155
A4: 46149 | B4: 46163 | C4: FM4039 | D4: SO4571 | E4: Cash Sale | F4: Shonisani Rambau Construction | G4: 24910.15 | H4: Sizwe Tshabalala | I4: In Progress | J4: CASH SALE - PAID | K4: c/w 1.5 kW 6 Pole 380 V Motor w/ Bird Screen (Qty: 1) | L4: =B4 -> 46163
A5: 46077 | B5: 46169 | C5: FM3874 | D5: SO4404 | E5: PO2174 | F5: ITD North Pty Ltd | G5: 94247.1 | H5: Mashudu Tshifularo | I5: In Progress | J5: CASH SALE – PARTIAL | K5: RDH 710 K2 - Nicotra Fan (Qty: 1) | L5: =B5 -> 46169
A6: 46069 | B6: 46170 | C6: FM3841 | D6: SO4372 | E6: PO2213 | F6: Hucra Fans | G6: 379993.35 | H6: Sales Agent Hucra Fans | I6: In Progress | J6: ACCOUNT - UP TO DATE | K6: SCL K11 MS - 11.0kW - 525V (Qty: 3) | L6: =B6 -> 46170
A7: 46112 | B7: 46170 | C7: FM3974 | D7: SO4502 | E7: 210719 | F7: Kenmare Moma Processing (Mauritius) Limited | G7: 103711 | H7: Sizwe Tshabalala | I7: In Progress | J7: ACCOUNT - UP TO DATE | K7: SCL-K10 MS-11kW - Item no 28000234 (Qty: 1) | L7: =B7 -> 46170
A8: 46112 | B8: 46170 | C8: FM3997 | D8: SO4525 | E8: 211035 | F8: Kenmare Moma Processing (Mauritius) Limited | G8: 83433 | H8: Sizwe Tshabalala | I8: In Progress | J8: ACCOUNT - UP TO DATE | K8: SCL-K08 MS-7.5kW (Qty: 1) | L8: =B8 -> 46170
A9: 46057 | B9: 46171 | C9: Pending | D9: SO4558 | E9: FMTA4398-Thabakgolo | F9: Oribi Air CC | G9: 427841.4 | H9: Mashudu Tshifularo | I9: Pending | K9: LINEO 250 QUIET-5.1.1 (Qty: 24), LINEO 315 QUIET-5.6.1 (Qty: 12) | L9: =B9 -> 46171
A10: 46111 | B10: 46171 | C10: FM3967 | D10: SO4492 | E10: PO260306 | F10: Alpha Air Ventilation Services | G10: 9014.21 | H10: Sizwe Tshabalala | I10: Pending | K10: MAJAX-2 500 c/w 0,55KW 4P 380V (Qty: 1), 500 Diam Counter Flange (Qty: 2) | L10: =B10 -> 46171
A11: 46111 | B11: 46171 | C11: FM3990 | D11: SO4517 | E11: PO:0000426 | F11: Compu Cool (Pty) Ltd | G11: 169353.6 | H11: Mashudu Tshifularo | I11: Pending | K11: UV710/3/6 (Qty: 6) | L11: =B11 -> 46171
A12: 46128 | B12: 46171 | C12: Pending | D12: SO4554 | E12: FMTA4599 | F12: Matla Solution Group | G12: 82900.05 | H12: Mashudu Tshifularo | I12: Pending | K12: LINEO 315 QUIET - EF 1 (Qty: 1), LINEO 250 QUIET - EF 2 (Qty: 1), LINEO 200 QUIET - EF 3 (Qty: 1), KDAXIS 200 - EF 4 (Qty: 1), KDAXIS 200 - EF 5 (Qty: 1), MAXFLO 630/250/14 A c/w 1,10KW 4P 380V - FA 1 (Qty: 1), 630 Diam Silencer 1.5D Podded (Qty: 2), 630 Diam Counter Flange (Qty: 2), 630 Diam Mounting Feet (Qty: 4), 630 to 1000 NDB GREEN Neoprene Floor Mounts (Qty: 8), MAXFLO 710/250/14 A c/w 1,10KW 4P 380V - FA 2 (Qty: 1), 710 Diam Silencer 1.5D Podded (Qty: 2), 710 Diam Counter Flange (Qty: 2), 710 Diam Mounting Feet (Qty: 4), 630 to 1000 NDB GREEN Neoprene Floor Mounts (Qty: 8) | L12: =B12 -> 46171
A13: 46142 | B13: 46171 | C13: Pending | D13: SO4556 | E13: Constitutional Hill | F13: LJ Trading & Projects (Pty) Ltd | G13: 554227.55 | H13: Simon Mokgola | I13: Pending | K13: Constitutional Hill (Qty: 1) | L13: =B13 -> 46171
A14: 46142 | B14: 46171 | C14: Pending | D14: SO4552 | E14: nan | F14: Neobionomics Services Pty Ltd | G14: 13711.09 | H14: Sizwe Tshabalala | I14: Pending | K14: MAJAX-2 630 c/w 0,75KW 4P 380V (Qty: 1) | L14: =B14 -> 46171
A15: 46142 | B15: 46171 | C15: Pending | D15: SO4553 | E15: FMTA4519 | F15: ST AIR SERVICES AND MAINTENANCE (PTY) LTD | G15: 426010.6 | H15: Simon Mokgola | I15: Pending | K15: Mimosa Mall Office Park (Qty: 1) | L15: =B15 -> 46171
A16: 46142 | B16: 46171 | C16: FM4036 | D16: SO4555 | E16: FM4035-FM4036 | F16: Michmat Projects | G16: 310411 | H16: Mashudu - R.O.A | I16: Pending | K16: MFAJAX-3 1250 c/w 45,00KW 4P 380V (Qty: 3), 1250 Diam Counter Flange (Qty: 6), 1250 Diam Mounting Feet (Qty: 6), 630 to 1000 NDB GREEN Neoprene Floor Mounts (Qty: 12), MAJAX-3 560 c/w 5,50KW 2P 380V (Qty: 2), 560 Diam Counter Flange (Qty: 4), 560 Diam Mounting Feet (Qty: 4), 315 to 560 NDA RED ANeoprene Floor Mounts (Qty: 8) | L16: =B16 -> 46171
A17: 46142 | B17: 46171 | C17: Pending | D17: SO4557 | E17: nan | F17: Vigeta Pty Ltd | G17: 204447 | H17: Simon Mokgola | I17: Pending | K17: 630 Diam Vertical Discharge BASE c/w 2.2kW 4P 380V (Qty: 10) | L17: =B17 -> 46171
F18: Total Value (All): | G18: =SUM(G3:G17) -> 2903365.5
F20: BREAKDOWN
F21: Cash Sale (May): | G21: =SUMIFS(G3:G17, J3:J17, "*CASH SALE*", L3:L17, ">="&EOMONTH(TODAY(),-1)+1, L3:L17, "<="&EOMONTH(TODAY(),0)) -> 138311.65 | I21: Cash Sale (June): | J21: =SUMIFS(G3:G17, J3:J17, "*CASH SALE*", L3:L17, ">="&EOMONTH(TODAY(),0)+1, L3:L17, "<="&EOMONTH(TODAY(),1)) -> 0
F22: Account (May): | G22: =SUMIFS(G3:G17, J3:J17, "*ACCOUNT*", L3:L17, ">="&EOMONTH(TODAY(),-1)+1, L3:L17, "<="&EOMONTH(TODAY(),0)) -> 567137.35 | I22: Account (June): | J22: =SUMIFS(G3:G17, J3:J17, "*ACCOUNT*", L3:L17, ">="&EOMONTH(TODAY(),0)+1, L3:L17, "<="&EOMONTH(TODAY(),1)) -> 0
A25: Date | B25: Delivery Date | C25: Job Number | D25: SO Number | E25: Customer Ref. | F25: Customer | G25: Total | H25: Sales Rep | I25: Status | J25: Payment Status | K25: Comments
F27: Due Today - Total: | G27: =SUM(G26:G26) -> 0
F29: Ready-Dispatch: | G29: =SUMIFS(G3:G17, I3:I17, "*Ready*Dispatch*") -> 0

Sheet 11.05.2026
A1: SALES ORDER REPORT | K1: =TODAY() -> 46171
A2: Date | B2: Delivery Date | C2: Job Number | D2: SO Number | E2: Customer Ref. | F2: Customer | G2: Total | H2: Sales Rep | I2: Status | J2: Payment Status | K2: Details | L2: Planned Delivery Date
A3: 46150 | B3: 46153.314 | C3: FM4041 | D3: SO4573 | E3: FM4041 | F3: Airetronic Maintenance & Sales (Pty) Ltd | G3: 8809 | H3: Simon Mokgola | I3: Ready-Dispatch | J3: ACCOUNT - UP TO DATE | K3: NEOLINEO-150/V (Qty: 3), Delivery to Durban (Qty: 1) | L3: =B3 -> 46153.314
A4: 46142 | B4: 46155 | C4: FM4031 | D4: SO4565 | E4: POAM26058144 | F4: Allbro Industries (PTY) Ltd | G4: 19154.4 | H4: Sizwe Tshabalala | I4: In Progress | J4: CASH SALE - PAID | K4: HV 7 c/w 0.45kw 6P 380v (Qty: 2), WEATHER LOUVRE 800(W)*800(H) HS NA (Qty: 2) | L4: =B4 -> 46155
A5: 46149 | B5: 46163 | C5: FM4039 | D5: SO4571 | E5: Cash Sale | F5: Shonisani Rambau Construction | G5: 24910.15 | H5: Sizwe Tshabalala | I5: In Progress | J5: CASH SALE - PAID | K5: UV c/w 1.5 kW 6 Pole 380 V Motor w/ Bird Screen (Qty: 1) | L5: =B5 -> 46163
A6: 46077 | B6: 46169 | C6: FM3874 | D6: SO4404 | E6: PO2174 | F6: ITD North Pty Ltd | G6: 94247.1 | H6: Mashudu Tshifularo | I6: In Progress | J6: CASH SALE – PARTIAL | K6: RDH 710 K2 - Nicotra Fan (Qty: 1) | L6: =B6 -> 46169
A7: 46069 | B7: 46170 | C7: FM3841 | D7: SO4372 | E7: PO2213 | F7: Hucra Fans | G7: 379993.35 | H7: Sales Agent Hucra Fans | I7: In Progress | J7: ACCOUNT - UP TO DATE | K7: SCL K11 MS - 11.0kW - 525V (Qty: 3) | L7: =B7 -> 46170
A8: 46112 | B8: 46170 | C8: FM3974 | D8: SO4502 | E8: 210719 | F8: Kenmare Moma Processing (Mauritius) Limited | G8: 103711 | H8: Sizwe Tshabalala | I8: In Progress | J8: ACCOUNT - UP TO DATE | K8: SCL-K10 MS-11kW - Item no 28000234 (Qty: 1) | L8: =B8 -> 46170
A9: 46112 | B9: 46170 | C9: FM3997 | D9: SO4525 | E9: 211035 | F9: Kenmare Moma Processing (Mauritius) Limited | G9: 83433 | H9: Sizwe Tshabalala | I9: In Progress | J9: ACCOUNT - UP TO DATE | K9: SCL-K08 MS-7.5kW (Qty: 1) | L9: =B9 -> 46170
A10: 46111 | B10: 46171 | C10: FM3967 | D10: SO4492 | E10: PO260306 | F10: Alpha Air Ventilation Services | G10: 9014.21 | H10: Sizwe Tshabalala | I10: On Hold | K10: MAJAX-2 500 c/w 0,55KW 4P 380V (Qty: 1), 500 Diam Counter Flange (Qty: 2) | L10: =B10 -> 46171
A11: 46111 | B11: 46171 | C11: FM3990 | D11: SO4517 | E11: PO:0000426 | F11: Compu Cool (Pty) Ltd | G11: 169353.6 | H11: Mashudu Tshifularo | I11: On Hold | J11: ACCOUNT - UP TO DATE | K11: UV710/3/6 (Qty: 6) | L11: =B11 -> 46171
A12: 46057 | B12: 46171 | C12: Pending | D12: SO4558 | E12: FMTA4398-Thabakgolo | F12: Oribi Air CC | G12: 427841.4 | H12: Mashudu Tshifularo | I12: Pending | K12: LINEO 250 QUIET-5.1.1 (Qty: 24), LINEO 315 QUIET-5.6.1 (Qty: 12) | L12: =B12 -> 46171
A13: 46128 | B13: 46171 | C13: Pending | D13: SO4554 | E13: FMTA4599 | F13: Matla Solution Group | G13: 82900.05 | H13: Mashudu Tshifularo | I13: Pending | K13: LINEO 315 QUIET - EF 1 (Qty: 1), LINEO 250 QUIET - EF 2 (Qty: 1), LINEO 200 QUIET - EF 3 (Qty: 1), KDAXIS 200 - EF 4 (Qty: 1), KDAXIS 200 - EF 5 (Qty: 1), MAXFLO 630/250/14 A c/w 1,10KW 4P 380V - FA 1 (Qty: 1), 630 Diam Silencer 1.5D Podded (Qty: 2), 630 Diam Counter Flange (Qty: 2), 630 Diam Mounting Feet (Qty: 4), 630 to 1000 NDB GREEN Neoprene Floor Mounts (Qty: 8), MAXFLO 710/250/14 A c/w 1,10KW 4P 380V - FA 2 (Qty: 1), 710 Diam Silencer 1.5D Podded (Qty: 2), 710 Diam Counter Flange (Qty: 2), 710 Diam Mounting Feet (Qty: 4), 630 to 1000 NDB GREEN Neoprene Floor Mounts (Qty: 8) | L13: =B13 -> 46171
A14: 46142 | B14: 46171 | C14: Pending | D14: SO4556 | E14: Constitutional Hill | F14: LJ Trading & Projects (Pty) Ltd | G14: 554227.55 | H14: Simon Mokgola | I14: Pending | K14: Constitutional Hill (Qty: 1) | L14: =B14 -> 46171
A15: 46142 | B15: 46171 | C15: Pending | D15: SO4552 | E15: nan | F15: Neobionomics Services Pty Ltd | G15: 13711.09 | H15: Sizwe Tshabalala | I15: Pending | K15: MAJAX-2 630 c/w 0,75KW 4P 380V (Qty: 1) | L15: =B15 -> 46171
A16: 46142 | B16: 46171 | C16: Pending | D16: SO4553 | E16: FMTA4519 | F16: ST AIR SERVICES AND MAINTENANCE (PTY) LTD | G16: 426010.6 | H16: Simon Mokgola | I16: Pending | K16: Mimosa Mall Office Park (Qty: 1) | L16: =B16 -> 46171
A17: 46142 | B17: 46171 | C17: FM4036 | D17: SO4555 | E17: FM4035-FM4036 | F17: Michmat Projects | G17: 310411 | H17: Mashudu - R.O.A | I17: Pending | K17: MFAJAX-3 1250 c/w 45,00KW 4P 380V (Qty: 3), 1250 Diam Counter Flange (Qty: 6), 1250 Diam Mounting Feet (Qty: 6), 630 to 1000 NDB GREEN Neoprene Floor Mounts (Qty: 12), MAJAX-3 560 c/w 5,50KW 2P 380V (Qty: 2), 560 Diam Counter Flange (Qty: 4), 560 Diam Mounting Feet (Qty: 4), 315 to 560 NDA RED ANeoprene Floor Mounts (Qty: 8) | L17: =B17 -> 46171
A18: 46142 | B18: 46171 | C18: Pending | D18: SO4557 | E18: nan | F18: Vigeta Pty Ltd | G18: 204447 | H18: Simon Mokgola | I18: Pending | K18: 630 Diam Vertical Discharge BASE c/w 2.2kW 4P 380V (Qty: 10) | L18: =B18 -> 46171
F19: Total Value (All): | G19: =SUM(G3:G18) -> 2912174.5
F21: BREAKDOWN
F22: Cash Sale (May): | G22: =SUMIFS(G3:G18, J3:J18, "*CASH SALE*", L3:L18, ">="&EOMONTH(TODAY(),-1)+1, L3:L18, "<="&EOMONTH(TODAY(),0)) -> 138311.65 | I22: Cash Sale (June): | J22: =SUMIFS(G3:G18, J3:J18, "*CASH SALE*", L3:L18, ">="&EOMONTH(TODAY(),0)+1, L3:L18, "<="&EOMONTH(TODAY(),1)) -> 0
F23: Account (May): | G23: =SUMIFS(G3:G18, J3:J18, "*ACCOUNT*", L3:L18, ">="&EOMONTH(TODAY(),-1)+1, L3:L18, "<="&EOMONTH(TODAY(),0)) -> 745299.95 | I23: Account (June): | J23: =SUMIFS(G3:G18, J3:J18, "*ACCOUNT*", L3:L18, ">="&EOMONTH(TODAY(),0)+1, L3:L18, "<="&EOMONTH(TODAY(),1)) -> 0
A25: Date | B25: Delivery Date | C25: Job Number | D25: SO Number | E25: Customer Ref. | F25: Customer | G25: Total | H25: Sales Rep | I25: Status | J25: Payment Status | K25: Comments
A26: 46150 | B26: 46153.314 | C26: FM4041 | D26: SO4573 | E26: FM4041 | F26: Airetronic Maintenance & Sales (Pty) Ltd | G26: 8809 | H26: Simon Mokgola | I26: In Progress | J26: ACCOUNT - UP TO DATE | K26: Delivery via Courier 11/05/2026
F27: Due Today - Total: | G27: =SUM(G26:G26) -> 8809
F29: Ready-Dispatch: | G29: =SUMIFS(G3:G18, I3:I18, "*Ready*Dispatch*") -> 8809

Sheet 12.05.2026
A1: SALES ORDER REPORT | K1: =TODAY() -> 46171
A2: Date | B2: Delivery Date | C2: Job Number | D2: SO Number | E2: Customer Ref. | F2: Customer | G2: Total | H2: Sales Rep | I2: Status | J2: Payment Status | K2: Details | L2: Planned Delivery Date
A3: 46142 | B3: 46154.349 | C3: Pending | D3: SO4556 | E3: Constitutional Hill | F3: LJ Trading & Projects (Pty) Ltd | G3: 554227.55 | H3: Simon Mokgola | I3: Pending | J3: =IFERROR(VLOOKUP(D3, '11.05.2026'!D:J, 7, FALSE), "") -> 0 | K3: Constitutional Hill (Qty: 1) | L3: =B3 -> 46154.349
A4: 46142 | B4: 46154.349 | C4: FM4031 | D4: SO4565 | E4: POAM26058144 | F4: Allbro Industries (PTY) Ltd | G4: 19154.4 | H4: Sizwe Tshabalala | I4: In Progress | J4: CASH SALE - PAID | K4: HV 7 c/w 0.45kw 6P 380v (Qty: 2), WEATHER LOUVRE 800(W)*800(H) HS NA (Qty: 2) | L4: =B4 -> 46154.349
A5: 46153 | B5: 46154.349 | C5: FM4043 | D5: SO4575 | E5: SAMPLE - BLOCK A | F5: Luft Technik (Pty) Ltd | G5: 0 | H5: Mashudu Tshifularo | I5: In Progress | J5: ACCOUNT - UP TO DATE | K5: MAXFLO 315/150/10 A c/w 0.37kW 2P 380V (Qty: 1) | L5: =B5 -> 46154.349
A6: 46153 | B6: 46154.349 | C6: FM4044 | D6: SO4576 | E6: FM4044 | F6: Systemair (Pty) Ltd | G6: 16067.8 | H6: Mashudu Tshifularo | I6: In Progress | J6: CASH SALE - PAID | K6: Tiracamino Chimney Fan for Chimney Tops (Qty: 1) | L6: =B6 -> 46154.349
A7: 46149 | B7: 46163 | C7: FM4039 | D7: SO4571 | E7: Cash Sale | F7: Shonisani Rambau Construction | G7: 24910.15 | H7: Sizwe Tshabalala | I7: In Progress | J7: CASH SALE - PAID | K7: c/w 1.5 kW 6 Pole 380 V Motor w/ Bird Screen (Qty: 1) | L7: =B7 -> 46163
A8: 46077 | B8: 46169 | C8: FM3874 | D8: SO4404 | E8: PO2174 | F8: ITD North Pty Ltd | G8: 94247.1 | H8: Mashudu Tshifularo | I8: In Progress | J8: CASH SALE – PARTIAL | K8: RDH 710 K2 - Nicotra Fan (Qty: 1) | L8: =B8 -> 46169
A9: 46069 | B9: 46170 | C9: FM3841 | D9: SO4372 | E9: PO2213 | F9: Hucra Fans | G9: 379993.35 | H9: Sales Agent Hucra Fans | I9: In Progress | J9: ACCOUNT - UP TO DATE | K9: SCL K11 MS - 11.0kW - 525V (Qty: 3) | L9: =B9 -> 46170
A10: 46112 | B10: 46170 | C10: FM3974 | D10: SO4502 | E10: 210719 | F10: Kenmare Moma Processing (Mauritius) Limited | G10: 103711 | H10: Sizwe Tshabalala | I10: In Progress | J10: ACCOUNT - UP TO DATE | K10: SCL-K10 MS-11kW - Item no 28000234 (Qty: 1) | L10: =B10 -> 46170
A11: 46112 | B11: 46170 | C11: FM3997 | D11: SO4525 | E11: 211035 | F11: Kenmare Moma Processing (Mauritius) Limited | G11: 83433 | H11: Sizwe Tshabalala | I11: In Progress | J11: ACCOUNT - UP TO DATE | K11: SCL-K08 MS-7.5kW (Qty: 1) | L11: =B11 -> 46170
A12: 46057 | B12: 46171 | C12: Pending | D12: SO4558 | E12: FMTA4398-Thabakgolo | F12: Oribi Air CC | G12: 427841.4 | H12: Mashudu Tshifularo | I12: Pending | J12: =IFERROR(VLOOKUP(D12, '11.05.2026'!D:J, 7, FALSE), "") -> 0 | K12: LINEO 250 QUIET-5.1.1 (Qty: 24), LINEO 315 QUIET-5.6.1 (Qty: 12) | L12: =B12 -> 46171
A13: 46111 | B13: 46171 | C13: FM3967 | D13: SO4492 | E13: PO260306 | F13: Alpha Air Ventilation Services | G13: 9014.21 | H13: Sizwe Tshabalala | I13: On Hold | J13: =IFERROR(VLOOKUP(D13, '11.05.2026'!D:J, 7, FALSE), "") -> 0 | K13: MAJAX-2 500 c/w 0,55KW 4P 380V (Qty: 1), 500 Diam Counter Flange (Qty: 2) | L13: =B13 -> 46171
A14: 46111 | B14: 46171 | C14: FM3990 | D14: SO4517 | E14: PO:0000426 | F14: Compu Cool (Pty) Ltd | G14: 169353.6 | H14: Mashudu Tshifularo | I14: On Hold | J14: =IFERROR(VLOOKUP(D14, '11.05.2026'!D:J, 7, FALSE), "") -> ACCOUNT - UP TO DATE | K14: UV710/3/6 (Qty: 6) | L14: =B14 -> 46171
A15: 46128 | B15: 46171 | C15: Pending | D15: SO4554 | E15: FMTA4599 | F15: Matla Solution Group | G15: 82900.05 | H15: Mashudu Tshifularo | I15: Pending | J15: =IFERROR(VLOOKUP(D15, '11.05.2026'!D:J, 7, FALSE), "") -> 0 | K15: LINEO 315 QUIET - EF 1 (Qty: 1), LINEO 250 QUIET - EF 2 (Qty: 1), LINEO 200 QUIET - EF 3 (Qty: 1), KDAXIS 200 - EF 4 (Qty: 1), KDAXIS 200 - EF 5 (Qty: 1), MAXFLO 630/250/14 A c/w 1,10KW 4P 380V - FA 1 (Qty: 1), 630 Diam Silencer 1.5D Podded (Qty: 2), 630 Diam Counter Flange (Qty: 2), 630 Diam Mounting Feet (Qty: 4), 630 to 1000 NDB GREEN Neoprene Floor Mounts (Qty: 8), MAXFLO 710/250/14 A c/w 1,10KW 4P 380V - FA 2 (Qty: 1), 710 Diam Silencer 1.5D Podded (Qty: 2), 710 Diam Counter Flange (Qty: 2), 710 Diam Mounting Feet (Qty: 4), 630 to 1000 NDB GREEN Neoprene Floor Mounts (Qty: 8) | L15: =B15 -> 46171
A16: 46142 | B16: 46171 | C16: Pending | D16: SO4552 | E16: nan | F16: Neobionomics Services Pty Ltd | G16: 13711.09 | H16: Sizwe Tshabalala | I16: Pending | J16: =IFERROR(VLOOKUP(D16, '11.05.2026'!D:J, 7, FALSE), "") -> 0 | K16: MAJAX-2 630 c/w 0,75KW 4P 380V (Qty: 1) | L16: =B16 -> 46171
A17: 46142 | B17: 46171 | C17: Pending | D17: SO4553 | E17: FMTA4519 | F17: ST AIR SERVICES AND MAINTENANCE (PTY) LTD | G17: 426010.6 | H17: Simon Mokgola | I17: Pending | J17: =IFERROR(VLOOKUP(D17, '11.05.2026'!D:J, 7, FALSE), "") -> 0 | K17: Mimosa Mall Office Park (Qty: 1) | L17: =B17 -> 46171
A18: 46142 | B18: 46171 | C18: FM4036 | D18: SO4555 | E18: FM4035-FM4036 | F18: Michmat Projects | G18: 310411 | H18: Mashudu - R.O.A | I18: Pending | J18: =IFERROR(VLOOKUP(D18, '11.05.2026'!D:J, 7, FALSE), "") -> 0 | K18: MFAJAX-3 1250 c/w 45,00KW 4P 380V (Qty: 3), 1250 Diam Counter Flange (Qty: 6), 1250 Diam Mounting Feet (Qty: 6), 630 to 1000 NDB GREEN Neoprene Floor Mounts (Qty: 12), MAJAX-3 560 c/w 5,50KW 2P 380V (Qty: 2), 560 Diam Counter Flange (Qty: 4), 560 Diam Mounting Feet (Qty: 4), 315 to 560 NDA RED ANeoprene Floor Mounts (Qty: 8) | L18: =B18 -> 46171
A19: 46142 | B19: 46171 | C19: Pending | D19: SO4557 | E19: nan | F19: Vigeta Pty Ltd | G19: 204447 | H19: Simon Mokgola | I19: Pending | J19: =IFERROR(VLOOKUP(D19, '11.05.2026'!D:J, 7, FALSE), "") -> 0 | K19: 630 Diam Vertical Discharge BASE c/w 2.2kW 4P 380V (Qty: 10) | L19: =B19 -> 46171
A20: 46154 | B20: 46173 | C20: FM4055 | D20: SO4577 | E20: FM4055 | F20: Vincent | G20: 12224.5 | H20: Simon Mokgola | I20: Pending | J20: =IFERROR(VLOOKUP(D20, '11.05.2026'!D:J, 7, FALSE), "") | K20: MAJAX-3 500 (BIFUCATED) c/w 0.55KW 4P 380V (Qty: 1) | L20: =B20 -> 46173
A21: 46154 | B21: 46173 | C21: FM4056 | D21: SO4578 | E21: FM4056 | F21: ADC Engineers | G21: 4322.85 | H21: Simon Mokgola | I21: Pending | J21: =IFERROR(VLOOKUP(D21, '11.05.2026'!D:J, 7, FALSE), "") | K21: RAD 150 (Qty: 1), RAD 250 (Qty: 1) | L21: =B21 -> 46173
F22: Total Value (All): | G22: =SUM(G3:G21) -> 2935980.7
F24: BREAKDOWN
F25: Cash Sale (May): | G25: =SUMIFS(G3:G21, J3:J21, "*CASH SALE*", L3:L21, ">="&EOMONTH(TODAY(),-1)+1, L3:L21, "<="&EOMONTH(TODAY(),0)) -> 154379.45 | I25: Cash Sale (June): | J25: =SUMIFS(G3:G21, J3:J21, "*CASH SALE*", L3:L21, ">="&EOMONTH(TODAY(),0)+1, L3:L21, "<="&EOMONTH(TODAY(),1)) -> 0
F26: Account (May): | G26: =SUMIFS(G3:G21, J3:J21, "*ACCOUNT*", L3:L21, ">="&EOMONTH(TODAY(),-1)+1, L3:L21, "<="&EOMONTH(TODAY(),0)) -> 736490.95 | I26: Account (June): | J26: =SUMIFS(G3:G21, J3:J21, "*ACCOUNT*", L3:L21, ">="&EOMONTH(TODAY(),0)+1, L3:L21, "<="&EOMONTH(TODAY(),1)) -> 0
A29: Date | B29: Delivery Date | C29: Job Number | D29: SO Number | E29: Customer Ref. | F29: Customer | G29: Total | H29: Sales Rep | I29: Status | J29: Payment Status | K29: Comments
A30: 46142 | B30: 46154.349 | C30: Pending | D30: SO4556 | E30: Constitutional Hill | F30: LJ Trading & Projects (Pty) Ltd | G30: 554227.55 | H30: Simon Mokgola | I30: Pending
A31: 46142 | B31: 46154.349 | C31: FM4031 | D31: SO4565 | E31: POAM26058144 | F31: Allbro Industries (PTY) Ltd | G31: 19154.4 | H31: Sizwe Tshabalala | I31: In Progress | J31: CASH SALE - PAID
A32: 46153 | B32: 46154.349 | C32: FM4043 | D32: SO4575 | E32: SAMPLE - BLOCK A | F32: Luft Technik (Pty) Ltd | G32: 0 | H32: Mashudu Tshifularo | I32: In Progress | J32: ACCOUNT - UP TO DATE
A33: 46153 | B33: 46154.349 | C33: FM4044 | D33: SO4576 | E33: FM4044 | F33: Systemair (Pty) Ltd | G33: 16067.8 | H33: Mashudu Tshifularo | I33: In Progress | J33: CASH SALE - PAID
F34: Due Today - Total: | G34: =SUM(G30:G33) -> 589449.75
F36: Ready-Dispatch: | G36: =SUMIFS(G3:G21, I3:I21, "*Ready*Dispatch*") -> 0
A39: Recommended Print Range: A1:L41
A40: Suggested Date for Next Update: 13.05.2026

Sheet 13.05.2026
A1: SALES ORDER REPORT | K1: =TODAY() -> 46171
A2: Date | B2: Delivery Date | C2: Job Number | D2: SO Number | E2: Customer Ref. | F2: Customer | G2: Total | H2: Sales Rep | I2: Status | J2: Payment Status | K2: Details | L2: Planned Delivery Date
A3: 46154 | B3: 46155.363 | C3: FM4026 | D3: SO4582 | E3: cash sale | F3: Carrons Corporate Maintenance | G3: 15092.97 | H3: Mashudu Tshifularo | I3: Ready - Dispatch | J3: CASH SALE - PAID | K3: V 300/12 AR (Qty: 2), Door grill 300mm x 300mm neck size (Qty: 3) | L3: =B3 -> 46155.363
A4: 46154 | B4: 46155.363 | C4: FM4060 | D4: SO4580 | E4: FM4060 | F4: Roto Tank | G4: 10263.75 | H4: Sizwe Tshabalala | I4: Ready - Dispatch | J4: CASH SALE - PAID | K4: CMP 616 2M (Qty: 1) | L4: =B4 -> 46155.363
A5: 46154 | B5: 46156 | C5: FM4059 | D5: SO4579 | E5: FM4057 | F5: Aircontech Technologies | G5: 50610.35 | H5: Simon Mokgola | I5: In Progress | J5: ACCOUNT - UP TO DATE | K5: MAXFLO 630/250/14 A c/w 0,75KW 4P 380V - EAF 04 (Qty: 1), 630 Diam Silencer 1.5D Podded (Qty: 2), 630 Diam Counter Flange (Qty: 2), 630 Diam Mounting Feet (Qty: 4), 630 to 1000 NDB GREEN Neoprene Floor Mounts (Qty: 8), CA/LINE-20 - EAF 01 (Qty: 1), 200 Diam Tube Silencer 600L (Qty: 2), CA/LINE-25 - EAF 02 (Qty: 1), 250 Diam Tube Silencer 600L (Qty: 2), MAXFLO 315/150/10 A c/w 0,55KW 2P 380V - EAF 03 (Qty: 1), 315 Diam Silencer 1.5D Podded (Qty: 2), 315 Diam Counter Flange (Qty: 2), 315 Diam Mounting Feet (Qty: 4), 315 to 560 NDA RED ANeoprene Floor Mounts (Qty: 8), KDAXIS 250 - WMF 01 (Qty: 1), KDAXIS 250 - WMF 02 (Qty: 1), KDAXIS 250 - WMF 03 (Qty: 1), KDAXIS 250 - WMF 04 (Qty: 1) | L5: =B5 -> 46156
A6: 46149 | B6: 46163 | C6: FM4039 | D6: SO4571 | E6: Cash Sale | F6: Shonisani Rambau Construction | G6: 24910.15 | H6: Sizwe Tshabalala | I6: In Progress | J6: CASH SALE - PAID | K6: UV c/w 1.5 kW 6 Pole 380 V Motor w/ Bird Screen (Qty: 1) | L6: =B6 -> 46163
A7: 46154 | B7: 46164 | C7: FM4055 | D7: SO4577 | E7: FM4055 | F7: Vincent | G7: 12224.5 | H7: Simon Mokgola | I7: In Progress | J7: CASH SALE - PAID | K7: MAJAX-3 500 (BIFUCATED) c/w 0.55KW 4P 380V (Qty: 1) | L7: =B7 -> 46164
A8: 46077 | B8: 46169 | C8: FM3874 | D8: SO4404 | E8: PO2174 | F8: ITD North Pty Ltd | G8: 94247.1 | H8: Mashudu Tshifularo | I8: In Progress | J8: CASH SALE – PARTIAL | K8: RDH 710 K2 - Nicotra Fan (Qty: 1) | L8: =B8 -> 46169
A9: 46069 | B9: 46170 | C9: FM3841 | D9: SO4372 | E9: PO2213 | F9: Hucra Fans | G9: 379993.35 | H9: Sales Agent Hucra Fans | I9: In Progress | J9: ACCOUNT - UP TO DATE | K9: SCL K11 MS - 11.0kW - 525V (Qty: 3) | L9: =B9 -> 46170
A10: 46112 | B10: 46170 | C10: FM3974 | D10: SO4502 | E10: 210719 | F10: Kenmare Moma Processing (Mauritius) Limited | G10: 103711 | H10: Sizwe Tshabalala | I10: In Progress | J10: ACCOUNT - UP TO DATE | K10: SCL-K10 MS-11kW - Item no 28000234 (Qty: 1) | L10: =B10 -> 46170
A11: 46112 | B11: 46170 | C11: FM3997 | D11: SO4525 | E11: 211035 | F11: Kenmare Moma Processing (Mauritius) Limited | G11: 83433 | H11: Sizwe Tshabalala | I11: In Progress | J11: ACCOUNT - UP TO DATE | K11: SCL-K08 MS-7.5kW (Qty: 1) | L11: =B11 -> 46170
A12: 46111 | B12: 46171 | C12: FM3967 | D12: SO4492 | E12: PO260306 | F12: Alpha Air Ventilation Services | G12: 9014.21 | H12: Sizwe Tshabalala | I12: On Hold | K12: MAJAX-2 500 c/w 0,55KW 4P 380V (Qty: 1), 500 Diam Counter Flange (Qty: 2) | L12: =B12 -> 46171
A13: 46111 | B13: 46171 | C13: FM3990 | D13: SO4517 | E13: PO:0000426 | F13: Compu Cool (Pty) Ltd | G13: 169353.6 | H13: Mashudu Tshifularo | I13: On Hold | J13: =IFERROR(VLOOKUP(D13, '12.05.2026'!D:J, 7, FALSE), "") -> ACCOUNT - UP TO DATE | K13: UV710/3/6 (Qty: 6) | L13: =B13 -> 46171
A14: 46142 | B14: 46171 | C14: FM4036 | D14: SO4555 | E14: FM4035-FM4036 | F14: Michmat Projects | G14: 310411 | H14: Mashudu - R.O.A | I14: Pending | K14: MFAJAX-3 1250 c/w 45,00KW 4P 380V (Qty: 3), 1250 Diam Counter Flange (Qty: 6), 1250 Diam Mounting Feet (Qty: 6), 630 to 1000 NDB GREEN Neoprene Floor Mounts (Qty: 12), MAJAX-3 560 c/w 5,50KW 2P 380V (Qty: 2), 560 Diam Counter Flange (Qty: 4), 560 Diam Mounting Feet (Qty: 4), 315 to 560 NDA RED ANeoprene Floor Mounts (Qty: 8) | L14: =B14 -> 46171
A15: 46057 | B15: 46171 | C15: Pending | D15: SO4558 | E15: FMTA4398-Thabakgolo | F15: Oribi Air CC | G15: 427841.4 | H15: Mashudu Tshifularo | I15: Pending | K15: LINEO 250 QUIET-5.1.1 (Qty: 24), LINEO 315 QUIET-5.6.1 (Qty: 12) | L15: =B15 -> 46171
A16: 46128 | B16: 46171 | C16: Pending | D16: SO4554 | E16: FMTA4599 | F16: Matla Solution Group | G16: 82900.05 | H16: Mashudu Tshifularo | I16: Pending | K16: LINEO 315 QUIET - EF 1 (Qty: 1), LINEO 250 QUIET - EF 2 (Qty: 1), LINEO 200 QUIET - EF 3 (Qty: 1), KDAXIS 200 - EF 4 (Qty: 1), KDAXIS 200 - EF 5 (Qty: 1), MAXFLO 630/250/14 A c/w 1,10KW 4P 380V - FA 1 (Qty: 1), 630 Diam Silencer 1.5D Podded (Qty: 2), 630 Diam Counter Flange (Qty: 2), 630 Diam Mounting Feet (Qty: 4), 630 to 1000 NDB GREEN Neoprene Floor Mounts (Qty: 8), MAXFLO 710/250/14 A c/w 1,10KW 4P 380V - FA 2 (Qty: 1), 710 Diam Silencer 1.5D Podded (Qty: 2), 710 Diam Counter Flange (Qty: 2), 710 Diam Mounting Feet (Qty: 4), 630 to 1000 NDB GREEN Neoprene Floor Mounts (Qty: 8) | L16: =B16 -> 46171
A17: 46142 | B17: 46171 | C17: Pending | D17: SO4556 | E17: Constitutional Hill | F17: LJ Trading & Projects (Pty) Ltd | G17: 554227.55 | H17: Simon Mokgola | I17: Pending | K17: Constitutional Hill (Qty: 1) | L17: =B17 -> 46171
A18: 46142 | B18: 46171 | C18: Pending | D18: SO4552 | E18: nan | F18: Neobionomics Services Pty Ltd | G18: 13711.09 | H18: Sizwe Tshabalala | I18: Pending | K18: MAJAX-2 630 c/w 0,75KW 4P 380V (Qty: 1) | L18: =B18 -> 46171
A19: 46142 | B19: 46171 | C19: Pending | D19: SO4553 | E19: FMTA4519 | F19: ST AIR SERVICES AND MAINTENANCE (PTY) LTD | G19: 426010.6 | H19: Simon Mokgola | I19: Pending | K19: Mimosa Mall Office Park (Qty: 1) | L19: =B19 -> 46171
A20: 46142 | B20: 46171 | C20: Pending | D20: SO4557 | E20: nan | F20: Vigeta Pty Ltd | G20: 204447 | H20: Simon Mokgola | I20: Pending | K20: 630 Diam Vertical Discharge BASE c/w 2.2kW 4P 380V (Qty: 10) | L20: =B20 -> 46171
A21: 46155 | B21: 46199 | C21: Pending | D21: SO4584 | E21: 211563 | F21: Kenmare Moma Processing (Mauritius) Limited | G21: 523356 | H21: Sizwe - R.O.A | I21: Pending | J21: =IFERROR(VLOOKUP(D21, '12.05.2026'!D:J, 7, FALSE), "") | K21: SCL-K11 TS-22kW - Item No 28000552 (Qty: 2) | L21: =B21 -> 46199
F22: Total Value (All): | G22: =SUM(G3:G21) -> 3495758.7
F24: BREAKDOWN
F25: Cash Sale (May): | G25: =SUMIFS(G3:G21, J3:J21, "*CASH SALE*", L3:L21, ">="&EOMONTH(TODAY(),-1)+1, L3:L21, "<="&EOMONTH(TODAY(),0)) -> 156738.47 | I25: Cash Sale (June): | J25: =SUMIFS(G3:G21, J3:J21, "*CASH SALE*", L3:L21, ">="&EOMONTH(TODAY(),0)+1, L3:L21, "<="&EOMONTH(TODAY(),1)) -> 0
F26: Account (May): | G26: =SUMIFS(G3:G21, J3:J21, "*ACCOUNT*", L3:L21, ">="&EOMONTH(TODAY(),-1)+1, L3:L21, "<="&EOMONTH(TODAY(),0)) -> 787101.3 | I26: Account (June): | J26: =SUMIFS(G3:G21, J3:J21, "*ACCOUNT*", L3:L21, ">="&EOMONTH(TODAY(),0)+1, L3:L21, "<="&EOMONTH(TODAY(),1)) -> 0
A28: Date | B28: Delivery Date | C28: Job Number | D28: SO Number | E28: Customer Ref. | F28: Customer | G28: Total | H28: Sales Rep | I28: Status | J28: Payment Status | K28: Comments
A29: 46154 | B29: 46155.363 | C29: FM4060 | D29: SO4580 | E29: FM4060 | F29: Roto Tank | G29: 10263.75 | H29: Sizwe Tshabalala | I29: Ready - Dispatch | J29: CASH SALE - PAID
A30: 46154 | B30: 46155.363 | C30: FM4026 | D30: SO4582 | E30: cash sale | F30: Carrons Corporate Maintenance | G30: 15092.97 | H30: Mashudu Tshifularo | I30: Ready - Dispatch | J30: CASH SALE - PAID
F31: Due Today - Total: | G31: =SUM(G29:G30) -> 25356.72
F33: Ready-Dispatch: | G33: =SUMIFS(G3:G21, I3:I21, "*Ready*Dispatch*") -> 25356.72

Sheet 14.05.2026
A1: SALES ORDER REPORT | K1: =TODAY() -> 46171
A2: Date | B2: Delivery Date | C2: Job Number | D2: SO Number | E2: Customer Ref. | F2: Customer | G2: Total | H2: Sales Rep | I2: Status | J2: Payment Status | K2: Details | L2: Planned Delivery Date
A3: 46154 | B3: 46156.327 | C3: FM4059 | D3: SO4579 | E3: FM4057 | F3: Aircontech Technologies | G3: 50610.35 | H3: Simon Mokgola | I3: In Progress | J3: ACCOUNT - UP TO DATE | K3: MAXFLO 630/250/14 A c/w 0,75KW 4P 380V - EAF 04 (Qty: 1), 630 Diam Silencer 1.5D Podded (Qty: 2), 630 Diam Counter Flange (Qty: 2), 630 Diam Mounting Feet (Qty: 4), 630 to 1000 NDB GREEN Neoprene Floor Mounts (Qty: 8), CA/LINE-20 - EAF 01 (Qty: 1), 200 Diam Tube Silencer 600L (Qty: 2), CA/LINE-25 - EAF 02 (Qty: 1), 250 Diam Tube Silencer 600L (Qty: 2), MAXFLO 315/150/10 A c/w 0,55KW 2P 380V - EAF 03 (Qty: 1), 315 Diam Silencer 1.5D Podded (Qty: 2), 315 Diam Counter Flange (Qty: 2), 315 Diam Mounting Feet (Qty: 4), 315 to 560 NDA RED ANeoprene Floor Mounts (Qty: 8), KDAXIS 250 - WMF 01 (Qty: 1), KDAXIS 250 - WMF 02 (Qty: 1), KDAXIS 250 - WMF 03 (Qty: 1), KDAXIS 250 - WMF 04 (Qty: 1) | L3: =B3 -> 46156.327
A4: 46154 | B4: 46156.327 | C4: FM4060 | D4: SO4580 | E4: FM4060 | F4: Roto Tank | G4: 10263.75 | H4: Sizwe Tshabalala | I4: Ready - Dispatch | J4: CASH SALE - PAID | K4: CMP 616 2M (Qty: 1) | L4: =B4 -> 46156.327
A5: 46154 | B5: 46161 | C5: FM4055 | D5: SO4577 | E5: FM4055 | F5: Vincent | G5: 12224.5 | H5: Simon Mokgola | I5: In Progress | J5: CASH SALE - PAID | K5: MAJAX-3 500 (BIFUCATED) c/w 0.55KW 4P 380V (Qty: 1) | L5: =B5 -> 46161
A6: 46149 | B6: 46163 | C6: FM4039 | D6: SO4571 | E6: Cash Sale | F6: Shonisani Rambau Construction | G6: 24910.15 | H6: Sizwe Tshabalala | I6: In Progress | J6: CASH SALE - PAID | K6: UV c/w 1.5 kW 6 Pole 380 V Motor w/ Bird Screen (Qty: 1) | L6: =B6 -> 46163
A7: 46077 | B7: 46169 | C7: FM3874 | D7: SO4404 | E7: PO2174 | F7: ITD North Pty Ltd | G7: 94247.1 | H7: Mashudu Tshifularo | I7: In Progress | J7: CASH SALE – PARTIAL | K7: RDH 710 K2 - Nicotra Fan (Qty: 1) | L7: =B7 -> 46169
A8: 46069 | B8: 46170 | C8: FM3841 | D8: SO4372 | E8: PO2213 | F8: Hucra Fans | G8: 379993.35 | H8: Sales Agent Hucra Fans | I8: In Progress | J8: ACCOUNT - UP TO DATE | K8: SCL K11 MS - 11.0kW - 525V (Qty: 3) | L8: =B8 -> 46170
A9: 46112 | B9: 46170 | C9: FM3974 | D9: SO4502 | E9: 210719 | F9: Kenmare Moma Processing (Mauritius) Limited | G9: 103711 | H9: Sizwe Tshabalala | I9: In Progress | J9: ACCOUNT - UP TO DATE | K9: SCL-K10 MS-11kW - Item no 28000234 (Qty: 1) | L9: =B9 -> 46170
A10: 46112 | B10: 46170 | C10: FM3997 | D10: SO4525 | E10: 211035 | F10: Kenmare Moma Processing (Mauritius) Limited | G10: 83433 | H10: Sizwe Tshabalala | I10: In Progress | J10: ACCOUNT - UP TO DATE | K10: SCL-K08 MS-7.5kW (Qty: 1) | L10: =B10 -> 46170
A11: 46111 | B11: 46171 | C11: FM3967 | D11: SO4492 | E11: PO260306 | F11: Alpha Air Ventilation Services | G11: 9014.21 | H11: Sizwe Tshabalala | I11: On Hold | K11: MAJAX-2 500 c/w 0,55KW 4P 380V (Qty: 1), 500 Diam Counter Flange (Qty: 2) | L11: =B11 -> 46171
A12: 46111 | B12: 46171 | C12: FM3990 | D12: SO4517 | E12: PO:0000426 | F12: Compu Cool (Pty) Ltd | G12: 169353.6 | H12: Mashudu Tshifularo | I12: On Hold | J12: =IFERROR(VLOOKUP(D12, '13.05.2026'!D:J, 7, FALSE), "") -> ACCOUNT - UP TO DATE | K12: UV710/3/6 (Qty: 6) | L12: =B12 -> 46171
A13: 46057 | B13: 46171 | C13: Pending | D13: SO4558 | E13: FMTA4398-Thabakgolo | F13: Oribi Air CC | G13: 427841.4 | H13: Mashudu Tshifularo | I13: Pending | K13: LINEO 250 QUIET-5.1.1 (Qty: 24), LINEO 315 QUIET-5.6.1 (Qty: 12) | L13: =B13 -> 46171
A14: 46128 | B14: 46171 | C14: Pending | D14: SO4554 | E14: FMTA4599 | F14: Matla Solution Group | G14: 82900.05 | H14: Mashudu Tshifularo | I14: Pending | K14: LINEO 315 QUIET - EF 1 (Qty: 1), LINEO 250 QUIET - EF 2 (Qty: 1), LINEO 200 QUIET - EF 3 (Qty: 1), KDAXIS 200 - EF 4 (Qty: 1), KDAXIS 200 - EF 5 (Qty: 1), MAXFLO 630/250/14 A c/w 1,10KW 4P 380V - FA 1 (Qty: 1), 630 Diam Silencer 1.5D Podded (Qty: 2), 630 Diam Counter Flange (Qty: 2), 630 Diam Mounting Feet (Qty: 4), 630 to 1000 NDB GREEN Neoprene Floor Mounts (Qty: 8), MAXFLO 710/250/14 A c/w 1,10KW 4P 380V - FA 2 (Qty: 1), 710 Diam Silencer 1.5D Podded (Qty: 2), 710 Diam Counter Flange (Qty: 2), 710 Diam Mounting Feet (Qty: 4), 630 to 1000 NDB GREEN Neoprene Floor Mounts (Qty: 8) | L14: =B14 -> 46171
A15: 46142 | B15: 46171 | C15: Pending | D15: SO4556 | E15: Constitutional Hill | F15: LJ Trading & Projects (Pty) Ltd | G15: 554227.55 | H15: Simon Mokgola | I15: Pending | K15: Constitutional Hill (Qty: 1) | L15: =B15 -> 46171
A16: 46142 | B16: 46171 | C16: Pending | D16: SO4552 | E16: nan | F16: Neobionomics Services Pty Ltd | G16: 13711.09 | H16: Sizwe Tshabalala | I16: Pending | K16: MAJAX-2 630 c/w 0,75KW 4P 380V (Qty: 1) | L16: =B16 -> 46171
A17: 46142 | B17: 46171 | C17: Pending | D17: SO4553 | E17: FMTA4519 | F17: ST AIR SERVICES AND MAINTENANCE (PTY) LTD | G17: 426010.6 | H17: Simon Mokgola | I17: Pending | K17: Mimosa Mall Office Park (Qty: 1) | L17: =B17 -> 46171
A18: 46142 | B18: 46171 | C18: FM4036 | D18: SO4555 | E18: FM4035-FM4036 | F18: Michmat Projects | G18: 310411 | H18: Mashudu - R.O.A | I18: Pending | K18: MFAJAX-3 1250 c/w 45,00KW 4P 380V (Qty: 3), 1250 Diam Counter Flange (Qty: 6), 1250 Diam Mounting Feet (Qty: 6), 630 to 1000 NDB GREEN Neoprene Floor Mounts (Qty: 12), MAJAX-3 560 c/w 5,50KW 2P 380V (Qty: 2), 560 Diam Counter Flange (Qty: 4), 560 Diam Mounting Feet (Qty: 4), 315 to 560 NDA RED ANeoprene Floor Mounts (Qty: 8) | L18: =B18 -> 46171
A19: 46142 | B19: 46171 | C19: Pending | D19: SO4557 | E19: nan | F19: Vigeta Pty Ltd | G19: 204447 | H19: Simon Mokgola | I19: Pending | K19: 630 Diam Vertical Discharge BASE c/w 2.2kW 4P 380V (Qty: 10) | L19: =B19 -> 46171
A20: 46155 | B20: 46199 | C20: FM4064 | D20: SO4584 | E20: 211563 | F20: Kenmare Moma Processing (Mauritius) Limited | G20: 523356 | H20: Sizwe - R.O.A | I20: Pending | J20: =IFERROR(VLOOKUP(D20, '13.05.2026'!D:J, 7, FALSE), "") | K20: SCL-K11 TS-22kW - Item No 28000552 (Qty: 2) | L20: =B20 -> 46199
F21: Total Value (All): | G21: =SUM(G3:G20) -> 3480665.7
F23: BREAKDOWN
F24: Cash Sale (May): | G24: =SUMIFS(G3:G20, J3:J20, "*CASH SALE*", L3:L20, ">="&EOMONTH(TODAY(),-1)+1, L3:L20, "<="&EOMONTH(TODAY(),0)) -> 141645.5 | I24: Cash Sale (June): | J24: =SUMIFS(G3:G20, J3:J20, "*CASH SALE*", L3:L20, ">="&EOMONTH(TODAY(),0)+1, L3:L20, "<="&EOMONTH(TODAY(),1)) -> 0
F25: Account (May): | G25: =SUMIFS(G3:G20, J3:J20, "*ACCOUNT*", L3:L20, ">="&EOMONTH(TODAY(),-1)+1, L3:L20, "<="&EOMONTH(TODAY(),0)) -> 787101.3 | I25: Account (June): | J25: =SUMIFS(G3:G20, J3:J20, "*ACCOUNT*", L3:L20, ">="&EOMONTH(TODAY(),0)+1, L3:L20, "<="&EOMONTH(TODAY(),1)) -> 0
A27: Date | B27: Delivery Date | C27: Job Number | D27: SO Number | E27: Customer Ref. | F27: Customer | G27: Total | H27: Sales Rep | I27: Status | J27: Payment Status | K27: Comments
A28: 46154 | B28: 46156.327 | C28: FM4060 | D28: SO4580 | E28: FM4060 | F28: Roto Tank | G28: 10263.75 | H28: Sizwe Tshabalala | I28: Ready - Dispatch | J28: CASH SALE - PAID
A29: 46154 | B29: 46156.327 | C29: FM4059 | D29: SO4579 | E29: FM4057 | F29: Aircontech Technologies | G29: 50610.35 | H29: Simon Mokgola | I29: In Progress | J29: ACCOUNT - UP TO DATE
F30: Due Today - Total: | G30: =SUM(G28:G29) -> 60874.1
F32: Ready-Dispatch: | G32: =SUMIFS(G3:G20, I3:I20, "*Ready*Dispatch*") -> 10263.75

Sheet 15.05.2026
A1: SALES ORDER REPORT | K1: =TODAY() -> 46171
A2: Date | B2: Delivery Date | C2: Job Number | D2: SO Number | E2: Customer Ref. | F2: Customer | G2: Total | H2: Sales Rep | I2: Status | J2: Payment Status | K2: Details | L2: Planned Delivery Date
A3: 46157 | B3: 46157.344 | C3: FM4072 | D3: SO4590 | E3: PO260025 | F3: Minelog Supplies cc | G3: 14821.2 | H3: Mashudu Tshifularo | I3: In Progress | J3: ACCOUNT - UP TO DATE | K3: CF9 - 4' CARTRIDGE (2), FL 9 4 FILTER (2) | L3: =B3 -> 46157.344
A4: 46154 | B4: 46157.344 | C4: FM4060 | D4: SO4580 | E4: FM4060 | F4: Roto Tank | G4: 10263.75 | H4: Sizwe Tshabalala | I4: Ready - Dispatch | J4: CASH SALE - PAID | K4: CMP 616 2M (1) | L4: =B4 -> 46157.344
A5: 46154 | B5: 46157.344 | C5: FM4059 | D5: SO4579 | E5: FM4057 | F5: Aircontech Technologies | G5: 50610.35 | H5: Simon Mokgola | I5: Ready - Dispatch | J5: ACCOUNT - UP TO DATE | K5: MAXFLO 630/250/14 A c/w 0,75KW 4P 380V - EAF 04 (1), 630 Diam Sil 1.5D Podded (2), 630 Diam C/Flange (2), 630 Diam M/Feet (4), 630 to 1000 NDB AVMs (8), CA/LINE-20 - EAF 01 (1), 200 Diam Tube Sil 600L (2), CA/LINE-25 - EAF 02 (1), 250 Diam Tube Sil 600L (2), MAXFLO 315/150/10 A c/w 0,55KW 2P 380V - EAF 03 (1), 315 Diam Sil 1.5D Podded (2), 315 Diam C/Flange (2), 315 Diam M/Feet (4), 315 to 560 NDA AVMs (8), KDAXIS 250 - WMF 01 (1), KDAXIS 250 - WMF 02 (1), KDAXIS 250 - WMF 03 (1), KDAXIS 250 - WMF 04 (1) | L5: =B5 -> 46157.344
A6: 46142 | B6: 46160 | C6: FM4022 | D6: SO4558 | E6: FMTA4398-Thabakgolo | F6: Oribi Air CC | G6: 89230.8 | H6: Mashudu Tshifularo | I6: In Progress | J6: CASH SALE - PAID | K6: KSB250 5.1.1 (8), KSB 315 5.6.1 (4) | L6: =B6 -> 46160
A7: 46154 | B7: 46161 | C7: FM4055 | D7: SO4577 | E7: FM4055 | F7: Vincent | G7: 12224.5 | H7: Simon Mokgola | I7: In Progress | J7: CASH SALE - PAID | K7: MAJAX-3 500 (BIFUCATED) c/w 0.55KW 4P 380V (1) | L7: =B7 -> 46161
A8: 46149 | B8: 46163 | C8: FM4039 | D8: SO4571 | E8: Cash Sale | F8: Shonisani Rambau Construction | G8: 24910.15 | H8: Sizwe Tshabalala | I8: In Progress | J8: CASH SALE - PAID | K8: UV c/w 1.5 kW 6 Pole 380 V Motor w/ Bird Screen (1) | L8: =B8 -> 46163
A9: 46077 | B9: 46169 | C9: FM3874 | D9: SO4404 | E9: PO2174 | F9: ITD North Pty Ltd | G9: 94247.1 | H9: Mashudu Tshifularo | I9: In Progress | J9: CASH SALE – PARTIAL | K9: RDH 710 K2 - Nicotra Fan (1) | L9: =B9 -> 46169
A10: 46069 | B10: 46170 | C10: FM3841 | D10: SO4372 | E10: PO2213 | F10: Hucra Fans | G10: 379993.35 | H10: Sales Agent Hucra Fans | I10: In Progress | J10: ACCOUNT - UP TO DATE | K10: SCL K11 MS - 11.0kW - 525V (3) | L10: =B10 -> 46170
A11: 46112 | B11: 46170 | C11: FM3974 | D11: SO4502 | E11: 210719 | F11: Kenmare Moma Processing (Mauritius) Limited | G11: 103711 | H11: Sizwe Tshabalala | I11: In Progress | J11: ACCOUNT - UP TO DATE | K11: SCL-K10 MS-11kW - Item no 28000234 (1) | L11: =B11 -> 46170
A12: 46112 | B12: 46170 | C12: FM3997 | D12: SO4525 | E12: 211035 | F12: Kenmare Moma Processing (Mauritius) Limited | G12: 83433 | H12: Sizwe Tshabalala | I12: In Progress | J12: ACCOUNT - UP TO DATE | K12: SCL-K08 MS-7.5kW (1) | L12: =B12 -> 46170
A13: 46111 | B13: 46171 | C13: FM3967 | D13: SO4492 | E13: PO260306 | F13: Alpha Air Ventilation Services | G13: 9014.21 | H13: Sizwe Tshabalala | I13: On Hold | J13: CASH SALE | K13: MAJAX-2 500 c/w 0,55KW 4P 380V (1), 500 Diam C/Flange (2) | L13: =B13 -> 46171
A14: 46111 | B14: 46171 | C14: FM3990 | D14: SO4517 | E14: PO:0000426 | F14: Compu Cool (Pty) Ltd | G14: 169353.6 | H14: Mashudu Tshifularo | I14: On Hold | J14: =IFERROR(VLOOKUP(D14, '14.05.2026'!D:J, 7, FALSE), "") -> ACCOUNT - UP TO DATE | K14: UV710/3/6 (6) | L14: =B14 -> 46171
A15: 46128 | B15: 46171 | C15: Pending | D15: SO4554 | E15: FMTA4599 | F15: Matla Solution Group | G15: 82900.05 | H15: Mashudu Tshifularo | I15: Pending | J15: ACCOUNT - UP TO DATE | K15: LINEO 315 QUIET - EF 1 (1), LINEO 250 QUIET - EF 2 (1), LINEO 200 QUIET - EF 3 (1), KDAXIS 200 - EF 4 (1), KDAXIS 200 - EF 5 (1), MAXFLO 630/250/14 A c/w 1,10KW 4P 380V - FA 1 (1), 630 Diam Sil 1.5D Podded (2), 630 Diam C/Flange (2), 630 Diam M/Feet (4), 630 to 1000 NDB AVMs (8), MAXFLO 710/250/14 A c/w 1,10KW 4P 380V - FA 2 (1), 710 Diam Sil 1.5D Podded (2), 710 Diam C/Flange (2), 710 Diam M/Feet (4), 630 to 1000 NDB AVMs (8) | L15: =B15 -> 46171
A16: 46142 | B16: 46171 | C16: Pending | D16: SO4556 | E16: Constitutional Hill | F16: LJ Trading & Projects (Pty) Ltd | G16: 554227.55 | H16: Simon Mokgola | I16: Pending | J16: CASH SALE | K16: Constitutional Hill (1) | L16: =B16 -> 46171
A17: 46142 | B17: 46171 | C17: Pending | D17: SO4552 | E17: nan | F17: Neobionomics Services Pty Ltd | G17: 13711.09 | H17: Sizwe Tshabalala | I17: Pending | J17: CASH SALE | K17: MAJAX-2 630 c/w 0,75KW 4P 380V (1) | L17: =B17 -> 46171
A18: 46142 | B18: 46171 | C18: Pending | D18: SO4553 | E18: FMTA4519 | F18: ST AIR SERVICES AND MAINTENANCE (PTY) LTD | G18: 426010.6 | H18: Simon Mokgola | I18: Pending | J18: ACCOUNT - UP TO DATE | K18: Mimosa Mall Office Park (1) | L18: =B18 -> 46171
A19: 46142 | B19: 46171 | C19: FM4036 | D19: SO4555 | E19: FM4035-FM4036 | F19: Michmat Projects | G19: 310411 | H19: Mashudu - R.O.A | I19: Pending | J19: CASH SALE | K19: MFAJAX-3 1250 c/w 45,00KW 4P 380V (3), 1250 Diam C/Flange (6), 1250 Diam M/Feet (6), 630 to 1000 NDB AVMs (12), MAJAX-3 560 c/w 5,50KW 2P 380V (2), 560 Diam C/Flange (4), 560 Diam M/Feet (4), 315 to 560 NDA AVMs (8) | L19: =B19 -> 46171
A20: 46142 | B20: 46171 | C20: Pending | D20: SO4557 | E20: nan | F20: Vigeta Pty Ltd | G20: 204447 | H20: Simon Mokgola | I20: Pending | J20: CASH SALE | K20: 630 Diam Vertical Discharge BASE c/w 2.2kW 4P 380V (10) | L20: =B20 -> 46171
A21: 46156 | B21: 46171 | C21: FM4070 | D21: SO4588 | E21: ELEIP002400315 -08 | F21: Elroi Trading Enterprise | G21: 234420.6 | H21: Simon Mokgola | I21: Pending | J21: CASH SALE | K21: MAXFLO 500/150/10 A c/w 0.37KW 4P 380V 304SS (1), 500 Diam M/Feet (2), SAL 630 (1), Majax-2 1250 20.D.8 c/w 18.5kW 4 Pole 380V (1), 1250 Diam Sil 1.5D Podded (2), 1250 Diam C/Flange (2), 1250 Diam M/Feet (4), Anti-Vibration Rubber Mounts (8) | L21: =B21 -> 46171
A22: 46155 | B22: 46199 | C22: FM4064 | D22: SO4584 | E22: 211563 | F22: Kenmare Moma Processing (Mauritius) Limited | G22: 523356 | H22: Sizwe - R.O.A | I22: Pending | J22: ACCOUNT - UP TO DATE | K22: SCL-K11 TS-22kW - Item No 28000552 (2) | L22: =B22 -> 46199
A23: 46156 | B23: 46203 | C23: FM4071 | D23: SO4589 | E23: 62179 | F23: Chabo & Joubert Air Conditioning (Pty) Ltd | G23: 6668.62 | H23: Sizwe Tshabalala | I23: In Progress | J23: ACCOUNT - UP TO DATE | K23: KAF 315 (2) | L23: =B23 -> 46203
F24: Total Value (All): | G24: =SUM(G3:G23) -> 3397965.5
F26: BREAKDOWN
F27: Cash Sale (May): | G27: =SUMIFS(G3:G23, J3:J23, "*CASH SALE*", L3:L23, ">="&EOMONTH(TODAY(),-1)+1, L3:L23, "<="&EOMONTH(TODAY(),0)) -> 1557107.8 | I27: Cash Sale (June): | J27: =SUMIFS(G3:G23, J3:J23, "*CASH SALE*", L3:L23, ">="&EOMONTH(TODAY(),0)+1, L3:L23, "<="&EOMONTH(TODAY(),1)) -> 0
F28: Account (May): | G28: =SUMIFS(G3:G23, J3:J23, "*ACCOUNT*", L3:L23, ">="&EOMONTH(TODAY(),-1)+1, L3:L23, "<="&EOMONTH(TODAY(),0)) -> 1310833.1 | I28: Account (June): | J28: =SUMIFS(G3:G23, J3:J23, "*ACCOUNT*", L3:L23, ">="&EOMONTH(TODAY(),0)+1, L3:L23, "<="&EOMONTH(TODAY(),1)) -> 530024.62
A30: Date | B30: Delivery Date | C30: Job Number | D30: SO Number | E30: Customer Ref. | F30: Customer | G30: Total | H30: Sales Rep | I30: Status | J30: Payment Status | K30: Comments
A31: 46154 | B31: 46157.344 | C31: FM4060 | D31: SO4580 | E31: FM4060 | F31: Roto Tank | G31: 10263.75 | H31: Sizwe Tshabalala | I31: Ready - Dispatch | J31: CASH SALE - PAID
A32: 46154 | B32: 46157.344 | C32: FM4059 | D32: SO4579 | E32: FM4057 | F32: Aircontech Technologies | G32: 50610.35 | H32: Simon Mokgola | I32: Ready - Dispatch | J32: ACCOUNT - UP TO DATE
A33: 46157 | B33: 46157.344 | C33: FM4072 | D33: SO4590 | E33: PO260025 | F33: Minelog Supplies cc | G33: 14821.2 | H33: Mashudu Tshifularo | I33: In Progress | J33: ACCOUNT - UP TO DATE
F34: Due Today - Total: | G34: =SUM(G31:G33) -> 75695.3
F36: Ready-Dispatch: | G36: =SUMIFS(G3:G23, I3:I23, "*Ready*Dispatch*") -> 60874.1

Sheet 18.05.2026
A1: SALES ORDER REPORT | K1: =TODAY() -> 46171
A2: Date | B2: Delivery Date | C2: Job Number | D2: SO Number | E2: Customer Ref. | F2: Customer | G2: Total | H2: Sales Rep | I2: Status | J2: Payment Status | K2: Details | L2: Planned Delivery Date
A3: 46154 | B3: 46160.387 | C3: FM4059 | D3: SO4579 | E3: FM4057 | F3: Aircontech Technologies | G3: 50610.35 | H3: SM | I3: Ready - Dispatch | J3: ACCOUNT - UP TO DATE | K3: MAXFLO 630/250/14 A c/w 0,75KW 4P 380V - EAF 04 (Qty: 1), 630 Diam Silencer 1.5D Podded (Qty: 2), 630 Diam Counter Flange (Qty: 2), 630 Diam Mounting Feet (Qty: 4), 630 to 1000 NDB GREEN Neoprene Floor Mounts (Qty: 8), CA/LINE-20 - EAF 01 (Qty: 1), 200 Diam Tube Silencer 600L (Qty: 2), CA/LINE-25 - EAF 02 (Qty: 1), 250 Diam Tube Silencer 600L (Qty: 2), MAXFLO 315/150/10 A c/w 0,55KW 2P 380V - EAF 03 (Qty: 1), 315 Diam Silencer 1.5D Podded (Qty: 2), 315 Diam Counter Flange (Qty: 2), 315 Diam Mounting Feet (Qty: 4), 315 to 560 NDA RED ANeoprene Floor Mounts (Qty: 8), KDAXIS 250 - WMF 01 (Qty: 1), KDAXIS 250 - WMF 02 (Qty: 1), KDAXIS 250 - WMF 03 (Qty: 1), KDAXIS 250 - WMF 04 (Qty: 1) | L3: =B3 -> 46160.387
A4: 46154 | B4: 46160.387 | C4: FM4060 | D4: SO4580 | E4: FM4060 | F4: Roto Tank | G4: 10263.75 | H4: ST | I4: Ready - Dispatch | J4: CASH SALE - PAID | K4: CMP 616 2M (Qty: 1) | L4: =B4 -> 46160.387
A5: 46142 | B5: 46161 | C5: FM4022 | D5: SO4558 | E5: FMTA4398-Thabakgolo | F5: Oribi Air CC | G5: 89230.8 | H5: MT | I5: In Progress | J5: CASH SALE - PAID | K5: KSB250 5.1.1 (Qty: 8), KSB 315 5.6.1 (Qty: 4) | L5: =B5 -> 46161
A6: 46160 | B6: 46161 | C6: FM4077 | D6: SO4595 | E6: FM4077 | F6: Duduzani | G6: 21986.85 | H6: SM | I6: In Progress | J6: CASH SALE - PAID | K6: MAJAX-3 630 c/w 1,10KW 4P 380V (Qty: 1), 630 Diam Silencer 1.5D Podded (Qty: 2), 630 Diam Counter Flange (Qty: 2), 630 Diam Mounting Feet (Qty: 4), 630 to 1000 NDB GREEN Neoprene Floor Mounts (Qty: 8) | L6: =B6 -> 46161
A7: 46157 | B7: 46162 | C7: FM4075 | D7: SO4593 | E7: PO146488 | F7: Howden Power a Div of Howden Africa (Pty) LTD | G7: 17622.6 | H7: ST | I7: In Progress | J7: ACCOUNT - UP TO DATE | K7: KDAXIS 300 (Qty: 3), 250/355 Wall Cowl Galvanized (Qty: 3), V 150/6 AR (Qty: 1), PIR Sensor (Qty: 1) | L7: =B7 -> 46162
A8: 46149 | B8: 46163 | C8: FM4039 | D8: SO4571 | E8: Cash Sale | F8: Shonisani Rambau Construction | G8: 24910.15 | H8: ST | I8: In Progress | J8: CASH SALE - PAID | K8: UV c/w 1.5 kW 6 Pole 380 V Motor w/ Bird Screen (Qty: 1) | L8: =B8 -> 46163
A9: 46157 | B9: 46164 | C9: FM4076 | D9: SO4594 | E9: PR 033836 | F9: Butec | G9: 21407.04 | H9: MT | I9: In Progress | J9: CASH SALE - P.O.D. | K9: MAXFLO 630/250/14 A c/w 2,20KW 4P 380V (Qty: 1), 630 Diam Melinex Silencer 1.5D Podded (Qty: 1), 630 Diam Melinex Silencer 1.0D Podded (Qty: 1), 630 Diam Counter Flange (Qty: 1), 630 Diam Mounting Feet (Qty: 4), 630 to 1000 NDB GREEN Neoprene Floor Mounts (Qty: 8) | L9: =B9 -> 46164
A10: 46077 | B10: 46169 | C10: FM3874 | D10: SO4404 | E10: PO2174 | F10: ITD North Pty Ltd | G10: 94247.1 | H10: MT | I10: In Progress | J10: CASH SALE – PARTIAL | K10: RDH 710 K2 - Nicotra Fan (Qty: 1) | L10: =B10 -> 46169
A11: 46069 | B11: 46170 | C11: FM3841 | D11: SO4372 | E11: PO2213 | F11: Hucra Fans | G11: 379993.35 | H11: S.A. HUCRA | I11: In Progress | J11: ACCOUNT - UP TO DATE | K11: SCL K11 MS - 11.0kW - 525V (Qty: 3) | L11: =B11 -> 46170
A12: 46112 | B12: 46170 | C12: FM3974 | D12: SO4502 | E12: 210719 | F12: Kenmare Moma Processing (Mauritius) Limited | G12: 103711 | H12: ST | I12: In Progress | J12: ACCOUNT - UP TO DATE | K12: SCL-K10 MS-11kW - Item no 28000234 (Qty: 1) | L12: =B12 -> 46170
A13: 46112 | B13: 46170 | C13: FM3997 | D13: SO4525 | E13: 211035 | F13: Kenmare Moma Processing (Mauritius) Limited | G13: 83433 | H13: ST | I13: In Progress | J13: ACCOUNT - UP TO DATE | K13: SCL-K08 MS-7.5kW (Qty: 1) | L13: =B13 -> 46170
A14: 46154 | B14: 46171 | C14: FM4055 | D14: SO4577 | E14: FM4055 | F14: Vincent | G14: 12224.5 | H14: SM | I14: In Progress | J14: CASH SALE - PAID | K14: MAJAX-3 500 (BIFUCATED) c/w 0.55KW 4P 380V (Qty: 1) | L14: =B14 -> 46171
A15: 46156 | B15: 46171 | C15: FM4070 | D15: SO4588 | E15: ELEIP002400315 -08 | F15: Elroi Trading Enterprise | G15: 234420.6 | H15: SM | I15: In Progress | J15: CASH SALE - PAID | K15: MAXFLO 500/150/10 A c/w 0.37KW 4P 380V 304SS (Qty: 1), 500 Diam Mounting Feet (Qty: 2), SAL 630 (Qty: 1), Majax-2 1250 20.D.8 c/w 18.5kW 4 Pole 380V (Qty: 1), 1250 Diam Silencer 1.5D Podded (Qty: 2), 1250 Diam Counter Flange (Qty: 2), 1250 Diam Mounting Feet (Qty: 4), PD3 RED - Anti Vibration Rubber Mounts (Qty: 8) | L15: =B15 -> 46171
A16: 46111 | B16: 46171 | C16: FM3967 | D16: SO4492 | E16: PO260306 | F16: Alpha Air Ventilation Services | G16: 9014.21 | H16: ST | I16: On Hold | J16: =IFERROR(VLOOKUP(D16, '15.05.2026'!D:J, 7, FALSE), "") -> CASH SALE | K16: MAJAX-2 500 c/w 0,55KW 4P 380V (Qty: 1), 500 Diam Counter Flange (Qty: 2) | L16: =B16 -> 46171
A17: 46111 | B17: 46171 | C17: FM3990 | D17: SO4517 | E17: PO:0000426 | F17: Compu Cool (Pty) Ltd | G17: 169353.6 | H17: MT | I17: On Hold | J17: =IFERROR(VLOOKUP(D17, '15.05.2026'!D:J, 7, FALSE), "") -> ACCOUNT - UP TO DATE | K17: UV710/3/6 (Qty: 6) | L17: =B17 -> 46171
A18: 46128 | B18: 46171 | C18: Pending | D18: SO4554 | E18: FMTA4599 | F18: Matla Solution Group | G18: 82900.05 | H18: MT | I18: Pending | J18: =IFERROR(VLOOKUP(D18, '15.05.2026'!D:J, 7, FALSE), "") -> ACCOUNT - UP TO DATE | K18: LINEO 315 QUIET - EF 1 (Qty: 1), LINEO 250 QUIET - EF 2 (Qty: 1), LINEO 200 QUIET - EF 3 (Qty: 1), KDAXIS 200 - EF 4 (Qty: 1), KDAXIS 200 - EF 5 (Qty: 1), MAXFLO 630/250/14 A c/w 1,10KW 4P 380V - FA 1 (Qty: 1), 630 Diam Silencer 1.5D Podded (Qty: 2), 630 Diam Counter Flange (Qty: 2), 630 Diam Mounting Feet (Qty: 4), 630 to 1000 NDB GREEN Neoprene Floor Mounts (Qty: 8), MAXFLO 710/250/14 A c/w 1,10KW 4P 380V - FA 2 (Qty: 1), 710 Diam Silencer 1.5D Podded (Qty: 2), 710 Diam Counter Flange (Qty: 2), 710 Diam Mounting Feet (Qty: 4), 630 to 1000 NDB GREEN Neoprene Floor Mounts (Qty: 8) | L18: =B18 -> 46171
A19: 46142 | B19: 46171 | C19: Pending | D19: SO4556 | E19: Constitutional Hill | F19: LJ Trading & Projects (Pty) Ltd | G19: 554227.55 | H19: SM | I19: Pending | J19: =IFERROR(VLOOKUP(D19, '15.05.2026'!D:J, 7, FALSE), "") -> CASH SALE | K19: Constitutional Hill (Qty: 1) | L19: =B19 -> 46171
A20: 46142 | B20: 46171 | C20: Pending | D20: SO4552 | E20: nan | F20: Neobionomics Services Pty Ltd | G20: 13711.09 | H20: ST | I20: Pending | J20: =IFERROR(VLOOKUP(D20, '15.05.2026'!D:J, 7, FALSE), "") -> CASH SALE | K20: MAJAX-2 630 c/w 0,75KW 4P 380V (Qty: 1) | L20: =B20 -> 46171
A21: 46142 | B21: 46171 | C21: Pending | D21: SO4553 | E21: FMTA4519 | F21: ST AIR SERVICES AND MAINTENANCE (PTY) LTD | G21: 426010.6 | H21: SM | I21: Pending | J21: =IFERROR(VLOOKUP(D21, '15.05.2026'!D:J, 7, FALSE), "") -> ACCOUNT - UP TO DATE | K21: Mimosa Mall Office Park (Qty: 1) | L21: =B21 -> 46171
A22: 46142 | B22: 46171 | C22: FM4036 | D22: SO4555 | E22: FM4035-FM4036 | F22: Michmat Projects | G22: 310411 | H22: MT - R.O.A. | I22: Pending | J22: =IFERROR(VLOOKUP(D22, '15.05.2026'!D:J, 7, FALSE), "") -> CASH SALE | K22: MFAJAX-3 1250 c/w 45,00KW 4P 380V (Qty: 3), 1250 Diam Counter Flange (Qty: 6), 1250 Diam Mounting Feet (Qty: 6), 630 to 1000 NDB GREEN Neoprene Floor Mounts (Qty: 12), MAJAX-3 560 c/w 5,50KW 2P 380V (Qty: 2), 560 Diam Counter Flange (Qty: 4), 560 Diam Mounting Feet (Qty: 4), 315 to 560 NDA RED ANeoprene Floor Mounts (Qty: 8) | L22: =B22 -> 46171
A23: 46142 | B23: 46171 | C23: Pending | D23: SO4557 | E23: nan | F23: Vigeta Pty Ltd | G23: 204447 | H23: SM | I23: Pending | J23: =IFERROR(VLOOKUP(D23, '15.05.2026'!D:J, 7, FALSE), "") -> CASH SALE | K23: 630 Diam Vertical Discharge BASE c/w 2.2kW 4P 380V (Qty: 10) | L23: =B23 -> 46171
A24: 46155 | B24: 46199 | C24: FM4064 | D24: SO4584 | E24: 211563 | F24: Kenmare Moma Processing (Mauritius) Limited | G24: 523356 | H24: ST - R.O.A. | I24: Pending | J24: =IFERROR(VLOOKUP(D24, '15.05.2026'!D:J, 7, FALSE), "") -> ACCOUNT - UP TO DATE | K24: SCL-K11 TS-22kW - Item No 28000552 (Qty: 2) | L24: =B24 -> 46199
F25: Total Value (All): | G25: =SUM(G3:G24) -> 3437492.2
F27: BREAKDOWN
F28: Cash Sale (May): | G28: =SUMIFS(G3:G24, J3:J24, "*CASH SALE*", L3:L24, ">="&EOMONTH(TODAY(),-1)+1, L3:L24, "<="&EOMONTH(TODAY(),0)) -> 1600501.6 | I28: Cash Sale (June): | J28: =SUMIFS(G3:G24, J3:J24, "*CASH SALE*", L3:L24, ">="&EOMONTH(TODAY(),0)+1, L3:L24, "<="&EOMONTH(TODAY(),1)) -> 0
F29: Account (May): | G29: =SUMIFS(G3:G24, J3:J24, "*ACCOUNT*", L3:L24, ">="&EOMONTH(TODAY(),-1)+1, L3:L24, "<="&EOMONTH(TODAY(),0)) -> 1313634.6 | I29: Account (June): | J29: =SUMIFS(G3:G24, J3:J24, "*ACCOUNT*", L3:L24, ">="&EOMONTH(TODAY(),0)+1, L3:L24, "<="&EOMONTH(TODAY(),1)) -> 523356
A31: Date | B31: Delivery Date | C31: Job Number | D31: SO Number | E31: Customer Ref. | F31: Customer | G31: Total | H31: Sales Rep | I31: Status | J31: Payment Status | K31: Comments
A32: 46154 | B32: 46160.387 | C32: FM4059 | D32: SO4579 | E32: FM4057 | F32: Aircontech Technologies | G32: 50610.35 | H32: SM | I32: Ready - Dispatch | J32: ACCOUNT - UP TO DATE
A33: 46154 | B33: 46160.387 | C33: FM4060 | D33: SO4580 | E33: FM4060 | F33: Roto Tank | G33: 10263.75 | H33: ST | I33: Ready - Dispatch | J33: CASH SALE - PAID
F34: Due Today - Total: | G34: =SUM(G32:G33) -> 60874.1
F36: Ready-Dispatch: | G36: =SUMIFS(G3:G24, I3:I24, "*Ready*Dispatch*") -> 60874.1

Sheet 19.05.2026
A1: SALES ORDER REPORT | K1: =TODAY() -> 46171
A2: Date | B2: Delivery Date | C2: Job Number | D2: SO Number | E2: Customer Ref. | F2: Customer | G2: Total | H2: Sales Rep | I2: Status | J2: Payment Status | K2: Details | L2: Planned Delivery Date
A3: 46142 | B3: 46161.397 | C3: FM4022 | D3: SO4558 | E3: FMTA4398-Thabakgolo | F3: Oribi Air CC | G3: 89230.8 | H3: Mashudu Tshifularo | I3: In Progress | J3: CASH SALE - PAID | K3: KSB250 5.1.1 (Qty: 8), KSB 315 5.6.1 (Qty: 4) | L3: =B3 -> 46161.397
A4: 46154 | B4: 46161.397 | C4: FM4060 | D4: SO4580 | E4: FM4060 | F4: Roto Tank | G4: 10263.75 | H4: Sizwe Tshabalala | I4: Ready - Dispatch | J4: CASH SALE - PAID | K4: CMP 616 2M (Qty: 1) | L4: =B4 -> 46161.397
A5: 46149 | B5: 46163 | C5: FM4039 | D5: SO4571 | E5: Cash Sale | F5: Shonisani Rambau Construction | G5: 24910.15 | H5: Sizwe Tshabalala | I5: In Progress | J5: CASH SALE - PAID | K5: UV 630-3-6 c/w 1.5 kW 6 Pole 380 V Motor w/ Bird Screen (Qty: 1) | L5: =B5 -> 46163
A6: 46157 | B6: 46164 | C6: FM4076 | D6: SO4594 | E6: PR 033836 | F6: Butec | G6: 21407.04 | H6: Mashudu Tshifularo | I6: In Progress | J6: ACCOUNT - OUTSTANDING | K6: MAXFLO 630/250/14 A c/w 2,20KW 4P 380V (Qty: 1), 630 Diam Melinex Silencer 1.5D Podded (Qty: 1), 630 Diam Melinex Silencer 1.0D Podded (Qty: 1), 630 Diam Counter Flange (Qty: 1), 630 Diam Mounting Feet (Qty: 4), 630 to 1000 NDB GREEN Neoprene Floor Mounts (Qty: 8) | L6: =B6 -> 46164
A7: 46157 | B7: 46164 | C7: FM4075 | D7: SO4593 | E7: PO146488 | F7: Howden Power a Div of Howden Africa (Pty) LTD | G7: 17622.6 | H7: Sizwe Tshabalala | I7: In Progress | J7: ACCOUNT - UP TO DATE | K7: KDAXIS 300 (Qty: 3), 250/355 Wall Cowl Galvanized (Qty: 3), V 150/6 AR (Qty: 1), PIR Sensor (Qty: 1) | L7: =B7 -> 46164
A8: 46160 | B8: 46164 | C8: FM4077 | D8: SO4595 | E8: FM4077 | F8: Duduzani | G8: 21986.85 | H8: Simon Mokgola | I8: In Progress | J8: ACCOUNT - UP TO DATE | K8: MAJAX-3 630 c/w 1,10KW 4P 380V (Qty: 1), 630 Diam Silencer 1.5D Podded (Qty: 2), 630 Diam Counter Flange (Qty: 2), 630 Diam Mounting Feet (Qty: 4), 630 to 1000 NDB GREEN Neoprene Floor Mounts (Qty: 8) | L8: =B8 -> 46164
A9: 46077 | B9: 46169 | C9: FM3874 | D9: SO4404 | E9: PO2174 | F9: ITD North Pty Ltd | G9: 94247.1 | H9: Mashudu Tshifularo | I9: In Progress | J9: CASH SALE – PARTIAL | K9: RDH 710 K2 - Nicotra Fan (Qty: 1) | L9: =B9 -> 46169
A10: 46069 | B10: 46170 | C10: FM3841 | D10: SO4372 | E10: PO2213 | F10: Hucra Fans | G10: 379993.35 | H10: Sales Agent Hucra Fans | I10: In Progress | J10: ACCOUNT - UP TO DATE | K10: SCL K11 MS - 11.0kW - 525V (Qty: 3) | L10: =B10 -> 46170
A11: 46112 | B11: 46170 | C11: FM3974 | D11: SO4502 | E11: 210719 | F11: Kenmare Moma Processing (Mauritius) Limited | G11: 103711 | H11: Sizwe Tshabalala | I11: In Progress | J11: ACCOUNT - UP TO DATE | K11: SCL-K10 MS-11kW - Item no 28000234 (Qty: 1) | L11: =B11 -> 46170
A12: 46112 | B12: 46170 | C12: FM3997 | D12: SO4525 | E12: 211035 | F12: Kenmare Moma Processing (Mauritius) Limited | G12: 83433 | H12: Sizwe Tshabalala | I12: In Progress | J12: ACCOUNT - UP TO DATE | K12: SCL-K08 MS-7.5kW (Qty: 1) | L12: =B12 -> 46170
A13: 46154 | B13: 46171 | C13: FM4055 | D13: SO4577 | E13: FM4055 | F13: Vincent | G13: 12224.5 | H13: Simon Mokgola | I13: In Progress | J13: CASH SALE - PAID | K13: MAJAX-3 500 (BIFUCATED) c/w 0.55KW 4P 380V (Qty: 1) | L13: =B13 -> 46171
A14: 46156 | B14: 46171 | C14: FM4070 | D14: SO4588 | E14: ELEIP002400315 -08 | F14: Elroi Trading Enterprise | G14: 234420.6 | H14: Simon Mokgola | I14: In Progress | J14: CASH SALE - PAID | K14: MAXFLO 500/150/10 A c/w 0.37KW 4P 380V 304SS (Qty: 1), 500 Diam Mounting Feet (Qty: 2), SAL 630 (Qty: 1), Majax-2 1250 20.D.8 c/w 18.5kW 4 Pole 380V (Qty: 1), 1250 Diam Silencer 1.5D Podded (Qty: 2), 1250 Diam Counter Flange (Qty: 2), 1250 Diam Mounting Feet (Qty: 4), PD3 RED - Anti Vibration Rubber Mounts (Qty: 8) | L14: =B14 -> 46171
A15: 46111 | B15: 46171 | C15: FM3967 | D15: SO4492 | E15: PO260306 | F15: Alpha Air Ventilation Services | G15: 9014.21 | H15: Sizwe Tshabalala | I15: On Hold | J15: =IFERROR(VLOOKUP(D15, '18.05.2026'!D:J, 7, FALSE), "") -> CASH SALE | K15: MAJAX-2 500 c/w 0,55KW 4P 380V (Qty: 1), 500 Diam Counter Flange (Qty: 2) | L15: =B15 -> 46171
A16: 46111 | B16: 46171 | C16: FM3990 | D16: SO4517 | E16: PO:0000426 | F16: Compu Cool (Pty) Ltd | G16: 169353.6 | H16: Mashudu Tshifularo | I16: On Hold | J16: =IFERROR(VLOOKUP(D16, '18.05.2026'!D:J, 7, FALSE), "") -> ACCOUNT - UP TO DATE | K16: UV710/3/6 (Qty: 6) | L16: =B16 -> 46171
A17: 46128 | B17: 46171 | C17: Pending | D17: SO4554 | E17: FMTA4599 | F17: Matla Solution Group | G17: 82900.05 | H17: Mashudu Tshifularo | I17: Pending | J17: =IFERROR(VLOOKUP(D17, '18.05.2026'!D:J, 7, FALSE), "") -> ACCOUNT - UP TO DATE | K17: LINEO 315 QUIET - EF 1 (Qty: 1), LINEO 250 QUIET - EF 2 (Qty: 1), LINEO 200 QUIET - EF 3 (Qty: 1), KDAXIS 200 - EF 4 (Qty: 1), KDAXIS 200 - EF 5 (Qty: 1), MAXFLO 630/250/14 A c/w 1,10KW 4P 380V - FA 1 (Qty: 1), 630 Diam Silencer 1.5D Podded (Qty: 2), 630 Diam Counter Flange (Qty: 2), 630 Diam Mounting Feet (Qty: 4), 630 to 1000 NDB GREEN Neoprene Floor Mounts (Qty: 8), MAXFLO 710/250/14 A c/w 1,10KW 4P 380V - FA 2 (Qty: 1), 710 Diam Silencer 1.5D Podded (Qty: 2), 710 Diam Counter Flange (Qty: 2), 710 Diam Mounting Feet (Qty: 4), 630 to 1000 NDB GREEN Neoprene Floor Mounts (Qty: 8) | L17: =B17 -> 46171
A18: 46142 | B18: 46171 | C18: Pending | D18: SO4556 | E18: Constitutional Hill | F18: LJ Trading & Projects (Pty) Ltd | G18: 554227.55 | H18: Simon Mokgola | I18: Pending | J18: =IFERROR(VLOOKUP(D18, '18.05.2026'!D:J, 7, FALSE), "") -> CASH SALE | K18: Constitutional Hill (Qty: 1) | L18: =B18 -> 46171
A19: 46142 | B19: 46171 | C19: Pending | D19: SO4553 | E19: FMTA4519 | F19: ST AIR SERVICES AND MAINTENANCE (PTY) LTD | G19: 426010.6 | H19: Simon Mokgola | I19: Pending | J19: =IFERROR(VLOOKUP(D19, '18.05.2026'!D:J, 7, FALSE), "") -> ACCOUNT - UP TO DATE | K19: Mimosa Mall Office Park (Qty: 1) | L19: =B19 -> 46171
A20: 46142 | B20: 46171 | C20: FM4036 | D20: SO4555 | E20: FM4035-FM4036 | F20: Michmat Projects | G20: 310411 | H20: Mashudu - R.O.A | I20: Pending | J20: =IFERROR(VLOOKUP(D20, '18.05.2026'!D:J, 7, FALSE), "") -> CASH SALE | K20: MFAJAX-3 1250 c/w 45,00KW 4P 380V (Qty: 3), 1250 Diam Counter Flange (Qty: 6), 1250 Diam Mounting Feet (Qty: 6), 630 to 1000 NDB GREEN Neoprene Floor Mounts (Qty: 12), MAJAX-3 560 c/w 5,50KW 2P 380V (Qty: 2), 560 Diam Counter Flange (Qty: 4), 560 Diam Mounting Feet (Qty: 4), 315 to 560 NDA RED ANeoprene Floor Mounts (Qty: 8) | L20: =B20 -> 46171
A21: 46142 | B21: 46171 | C21: Pending | D21: SO4557 | E21: nan | F21: Vigeta Pty Ltd | G21: 204447 | H21: Simon Mokgola | I21: Pending | J21: =IFERROR(VLOOKUP(D21, '18.05.2026'!D:J, 7, FALSE), "") -> CASH SALE | K21: 630 Diam Vertical Discharge BASE c/w 2.2kW 4P 380V (Qty: 10) | L21: =B21 -> 46171
A22: 46160 | B22: 46171 | C22: FM4080 | D22: SO4597 | E22: FM4078-4081 - REA VAYA - ROOF LEVEL | F22: TESLA COMMS | G22: 75285.9 | H22: Simon Mokgola | I22: Pending | J22: CASH SALE - PAID | K22: MAXFLO 630/250/14 A c/w 1,50KW 4P 380V (EAF01 - Admin Roof Level Fan) (Qty: 1), 630 Diam Silencer 1.5D Podded (Qty: 2), 630 Diam Counter Flange (Qty: 2), 630 Diam Mounting Feet (Qty: 4), 630 to 1000 NDB GREEN Neoprene Floor Mounts (Qty: 8), MAXFLO 630/250/14 A c/w 0,75KW 4P 380V (FAF02 - Admin Roof Level Fan) (Qty: 1), 630 Diam Silencer 1.5D Podded (Qty: 2), 630 Diam Counter Flange (Qty: 2), 630 Diam Mounting Feet (Qty: 4), 630 to 1000 NDB GREEN Neoprene Floor Mounts (Qty: 8), LINEO 315 (EAF01 - Admin Mezzanine Fan) (Qty: 1), 315 Diam Tube Silencer 600L (Qty: 2), MAXFLO 315/150/10 A c/w 0,55KW 2P 380V (EAF02 - Admin Mezzanine Fan) (Qty: 1), 315 Diam Silencer 1.5D Podded (Qty: 2), 315 Diam Counter Flange (Qty: 2), 315 Diam Mounting Feet (Qty: 4), 315 to 560 NDA RED ANeoprene Floor Mounts (Qty: 8) | L22: =B22 -> 46171
A23: 46155 | B23: 46199 | C23: FM4064 | D23: SO4584 | E23: 211563 | F23: Kenmare Moma Processing (Mauritius) Limited | G23: 523356 | H23: Sizwe - R.O.A | I23: Pending | J23: =IFERROR(VLOOKUP(D23, '18.05.2026'!D:J, 7, FALSE), "") -> ACCOUNT - UP TO DATE | K23: SCL-K11 TS-22kW - Item No 28000552 (Qty: 2) | L23: =B23 -> 46199
F24: Total Value (All): | G24: =SUM(G3:G23) -> 3448456.6
F26: BREAKDOWN
F27: Cash Sale (May): | G27: =SUMIFS(G3:G23, J3:J23, "*CASH SALE*", L3:L23, ">="&EOMONTH(TODAY(),-1)+1, L3:L23, "<="&EOMONTH(TODAY(),0)) -> 1618682.6 | I27: Cash Sale (June): | J27: =SUMIFS(G3:G23, J3:J23, "*CASH SALE*", L3:L23, ">="&EOMONTH(TODAY(),0)+1, L3:L23, "<="&EOMONTH(TODAY(),1)) -> 0
F28: Account (May): | G28: =SUMIFS(G3:G23, J3:J23, "*ACCOUNT*", L3:L23, ">="&EOMONTH(TODAY(),-1)+1, L3:L23, "<="&EOMONTH(TODAY(),0)) -> 1306418.1 | I28: Account (June): | J28: =SUMIFS(G3:G23, J3:J23, "*ACCOUNT*", L3:L23, ">="&EOMONTH(TODAY(),0)+1, L3:L23, "<="&EOMONTH(TODAY(),1)) -> 523356
A30: Date | B30: Delivery Date | C30: Job Number | D30: SO Number | E30: Customer Ref. | F30: Customer | G30: Total | H30: Sales Rep | I30: Status | J30: Payment Status | K30: Comments
A31: 46154 | B31: 46161.397 | C31: FM4060 | D31: SO4580 | E31: FM4060 | F31: Roto Tank | G31: 10263.75 | H31: Sizwe Tshabalala | I31: Ready - Dispatch | J31: CASH SALE - PAID
A32: 46142 | B32: 46161.397 | C32: FM4022 | D32: SO4558 | E32: FMTA4398-Thabakgolo | F32: Oribi Air CC | G32: 89230.8 | H32: Mashudu Tshifularo | I32: In Progress | J32: CASH SALE - PAID
F33: Due Today - Total: | G33: =SUM(G31:G32) -> 99494.55
F35: Ready-Dispatch: | G35: =SUMIFS(G3:G23, I3:I23, "*Ready*Dispatch*") -> 10263.75

Sheet 20.05.2026
A1: SALES ORDER REPORT | K1: =TODAY() -> 46171
A2: Date | B2: Delivery Date | C2: Job Number | D2: SO Number | E2: Customer Ref. | F2: Customer | G2: Total | H2: Sales Rep | I2: Status | J2: Payment Status | K2: Details | L2: Planned Delivery Date
A3: 46154 | B3: 46162 | C3: FM4055 | D3: SO4577 | E3: FM4055 | F3: Vincent | G3: 12224.5 | H3: SM | I3: In Progress | J3: CASH SALE - PAID | K3: MAJAX-3 500 (BIFUCATED) c/w 0.55KW 4P 380V (Qty: 1) | L3: =B3 -> 46162
A4: 46142 | B4: 46162.325 | C4: FM4022 | D4: SO4558 | E4: FMTA4398-Thabakgolo | F4: Oribi Air CC | G4: 89230.8 | H4: MT | I4: In Progress | J4: CASH SALE - PAID | K4: KSB250 5.1.1 (Qty: 8), KSB 315 5.6.1 (Qty: 4) | L4: =B4 -> 46162.325
A5: 46154 | B5: 46162.325 | C5: FM4060 | D5: SO4580 | E5: FM4060 | F5: Roto Tank | G5: 10263.75 | H5: ST | I5: Ready - Dispatch | J5: CASH SALE - PAID | K5: CMP 616 2M (Qty: 1) | L5: =B5 -> 46162.325
A6: 46149 | B6: 46163 | C6: FM4039 | D6: SO4571 | E6: Cash Sale | F6: Shonisani Rambau Construction | G6: 24910.15 | H6: ST | I6: In Progress | J6: CASH SALE - PAID | K6: UV 630-3-6 c/w 1.5 kW 6 Pole 380 V Motor w/ Bird Screen (Qty: 1) | L6: =B6 -> 46163
A7: 46157 | B7: 46164 | C7: FM4076 | D7: SO4594 | E7: PR 033836 | F7: Butec | G7: 21407.04 | H7: MT | I7: In Progress | J7: CASH SALE - C.O.D. | K7: MAXFLO 630/250/14 A c/w 2,20KW 4P 380V (Qty: 1), 630 Diam Melinex Silencer 1.5D Podded (Qty: 1), 630 Diam Melinex Silencer 1.0D Podded (Qty: 1), 630 Diam Counter Flange (Qty: 1), 630 Diam Mounting Feet (Qty: 4), 630 to 1000 NDB GREEN Neoprene Floor Mounts (Qty: 8) | L7: =B7 -> 46164
A8: 46157 | B8: 46164 | C8: FM4075 | D8: SO4593 | E8: PO146488 | F8: Howden Power a Div of Howden Africa (Pty) LTD | G8: 17622.6 | H8: ST | I8: In Progress | J8: ACCOUNT - UP TO DATE | K8: KDAXIS 300 (Qty: 3), 250/355 Wall Cowl Galvanized (Qty: 3), V 150/6 AR (Qty: 1), PIR Sensor (Qty: 1) | L8: =B8 -> 46164
A9: 46160 | B9: 46164 | C9: FM4077 | D9: SO4595 | E9: FM4077 | F9: Duduzani | G9: 21986.85 | H9: SM | I9: In Progress | J9: ACCOUNT - UP TO DATE | K9: MAJAX-3 630 c/w 1,10KW 4P 380V (Qty: 1), 630 Diam Silencer 1.5D Podded (Qty: 2), 630 Diam Counter Flange (Qty: 2), 630 Diam Mounting Feet (Qty: 4), 630 to 1000 NDB GREEN Neoprene Floor Mounts (Qty: 8) | L9: =B9 -> 46164
A10: 46160 | B10: 46164 | C10: FM4080 | D10: SO4597 | E10: FM4078-4081 - REA VAYA - ROOF LEVEL | F10: TESLA COMMS | G10: 75285.9 | H10: SM | I10: In Progress | J10: CASH SALE - PAID | K10: MAXFLO 630/250/14 A c/w 1,50KW 4P 380V (EAF01 - Admin Roof Level Fan) (Qty: 1), 630 Diam Silencer 1.5D Podded (Qty: 2), 630 Diam Counter Flange (Qty: 2), 630 Diam Mounting Feet (Qty: 4), 630 to 1000 NDB GREEN Neoprene Floor Mounts (Qty: 8), MAXFLO 630/250/14 A c/w 0,75KW 4P 380V (FAF02 - Admin Roof Level Fan) (Qty: 1), 630 Diam Silencer 1.5D Podded (Qty: 2), 630 Diam Counter Flange (Qty: 2), 630 Diam Mounting Feet (Qty: 4), 630 to 1000 NDB GREEN Neoprene Floor Mounts (Qty: 8), LINEO 315 (EAF01 - Admin Mezzanine Fan) (Qty: 1), 315 Diam Tube Silencer 600L (Qty: 2), MAXFLO 315/150/10 A c/w 0,55KW 2P 380V (EAF02 - Admin Mezzanine Fan) (Qty: 1), 315 Diam Silencer 1.5D Podded (Qty: 2), 315 Diam Counter Flange (Qty: 2), 315 Diam Mounting Feet (Qty: 4), 315 to 560 NDA RED ANeoprene Floor Mounts (Qty: 8) | L10: =B10 -> 46164
A11: 46077 | B11: 46169 | C11: FM3874 | D11: SO4404 | E11: PO2174 | F11: ITD North Pty Ltd | G11: 94247.1 | H11: MT | I11: In Progress | J11: CASH SALE – PARTIAL | K11: RDH 710 K2 - Nicotra Fan (Qty: 1) | L11: =B11 -> 46169
A12: 46069 | B12: 46170 | C12: FM3841 | D12: SO4372 | E12: PO2213 | F12: Hucra Fans | G12: 379993.35 | H12: S.A - HUCRA | I12: In Progress | J12: ACCOUNT - UP TO DATE | K12: SCL K11 MS - 11.0kW - 525V (Qty: 3) | L12: =B12 -> 46170
A13: 46112 | B13: 46170 | C13: FM3974 | D13: SO4502 | E13: 210719 | F13: Kenmare Moma Processing (Mauritius) Limited | G13: 103711 | H13: ST | I13: In Progress | J13: ACCOUNT - UP TO DATE | K13: SCL-K10 MS-11kW - Item no 28000234 (Qty: 1) | L13: =B13 -> 46170
A14: 46112 | B14: 46170 | C14: FM3997 | D14: SO4525 | E14: 211035 | F14: Kenmare Moma Processing (Mauritius) Limited | G14: 83433 | H14: ST | I14: In Progress | J14: ACCOUNT - UP TO DATE | K14: SCL-K08 MS-7.5kW (Qty: 1) | L14: =B14 -> 46170
A15: 46156 | B15: 46171 | C15: FM4070 | D15: SO4588 | E15: ELEIP002400315 -08 | F15: Elroi Trading Enterprise | G15: 234420.6 | H15: SM | I15: In Progress | J15: CASH SALE - PAID | K15: MAXFLO 500/150/10 A c/w 0.37KW 4P 380V 304SS (Qty: 1), 500 Diam Mounting Feet (Qty: 2), SAL 630 (Qty: 1), Majax-2 1250 20.D.8 c/w 18.5kW 4 Pole 380V (Qty: 1), 1250 Diam Silencer 1.5D Podded (Qty: 2), 1250 Diam Counter Flange (Qty: 2), 1250 Diam Mounting Feet (Qty: 4), PD3 RED - Anti Vibration Rubber Mounts (Qty: 8) | L15: =B15 -> 46171
A16: 46111 | B16: 46171 | C16: FM3967 | D16: SO4492 | E16: PO260306 | F16: Alpha Air Ventilation Services | G16: 9014.21 | H16: ST | I16: On Hold | J16: =IFERROR(VLOOKUP(D16, '19.05.2026'!D:J, 7, FALSE), "") -> CASH SALE | K16: MAJAX-2 500 c/w 0,55KW 4P 380V (Qty: 1), 500 Diam Counter Flange (Qty: 2) | L16: =B16 -> 46171
A17: 46111 | B17: 46171 | C17: FM3990 | D17: SO4517 | E17: PO:0000426 | F17: Compu Cool (Pty) Ltd | G17: 169353.6 | H17: MT | I17: On Hold | J17: =IFERROR(VLOOKUP(D17, '19.05.2026'!D:J, 7, FALSE), "") -> ACCOUNT - UP TO DATE | K17: UV710/3/6 (Qty: 6) | L17: =B17 -> 46171
A18: 46128 | B18: 46171 | C18: Pending | D18: SO4554 | E18: FMTA4599 | F18: Matla Solution Group | G18: 82900.05 | H18: MT | I18: Pending | J18: =IFERROR(VLOOKUP(D18, '19.05.2026'!D:J, 7, FALSE), "") -> ACCOUNT - UP TO DATE | K18: LINEO 315 QUIET - EF 1 (Qty: 1), LINEO 250 QUIET - EF 2 (Qty: 1), LINEO 200 QUIET - EF 3 (Qty: 1), KDAXIS 200 - EF 4 (Qty: 1), KDAXIS 200 - EF 5 (Qty: 1), MAXFLO 630/250/14 A c/w 1,10KW 4P 380V - FA 1 (Qty: 1), 630 Diam Silencer 1.5D Podded (Qty: 2), 630 Diam Counter Flange (Qty: 2), 630 Diam Mounting Feet (Qty: 4), 630 to 1000 NDB GREEN Neoprene Floor Mounts (Qty: 8), MAXFLO 710/250/14 A c/w 1,10KW 4P 380V - FA 2 (Qty: 1), 710 Diam Silencer 1.5D Podded (Qty: 2), 710 Diam Counter Flange (Qty: 2), 710 Diam Mounting Feet (Qty: 4), 630 to 1000 NDB GREEN Neoprene Floor Mounts (Qty: 8) | L18: =B18 -> 46171
A19: 46142 | B19: 46171 | C19: Pending | D19: SO4556 | E19: Constitutional Hill | F19: LJ Trading & Projects (Pty) Ltd | G19: 554227.55 | H19: SM | I19: Pending | J19: =IFERROR(VLOOKUP(D19, '19.05.2026'!D:J, 7, FALSE), "") -> CASH SALE | K19: Constitutional Hill (Qty: 1) | L19: =B19 -> 46171
A20: 46142 | B20: 46171 | C20: Pending | D20: SO4553 | E20: FMTA4519 | F20: ST AIR SERVICES AND MAINTENANCE (PTY) LTD | G20: 426010.6 | H20: SM | I20: Pending | J20: =IFERROR(VLOOKUP(D20, '19.05.2026'!D:J, 7, FALSE), "") -> ACCOUNT - UP TO DATE | K20: Mimosa Mall Office Park (Qty: 1) | L20: =B20 -> 46171
A21: 46142 | B21: 46171 | C21: FM4036 | D21: SO4555 | E21: FM4035-FM4036 | F21: Michmat Projects | G21: 310411 | H21: MT-R.O.A | I21: Pending | J21: =IFERROR(VLOOKUP(D21, '19.05.2026'!D:J, 7, FALSE), "") -> CASH SALE | K21: MFAJAX-3 1250 c/w 45,00KW 4P 380V (Qty: 3), 1250 Diam Counter Flange (Qty: 6), 1250 Diam Mounting Feet (Qty: 6), 630 to 1000 NDB GREEN Neoprene Floor Mounts (Qty: 12), MAJAX-3 560 c/w 5,50KW 2P 380V (Qty: 2), 560 Diam Counter Flange (Qty: 4), 560 Diam Mounting Feet (Qty: 4), 315 to 560 NDA RED ANeoprene Floor Mounts (Qty: 8) | L21: =B21 -> 46171
A22: 46142 | B22: 46171 | C22: Pending | D22: SO4557 | E22: nan | F22: Vigeta Pty Ltd | G22: 204447 | H22: SM | I22: Pending | J22: =IFERROR(VLOOKUP(D22, '19.05.2026'!D:J, 7, FALSE), "") -> CASH SALE | K22: 630 Diam Vertical Discharge BASE c/w 2.2kW 4P 380V (Qty: 10) | L22: =B22 -> 46171
A23: 46155 | B23: 46199 | C23: FM4064 | D23: SO4584 | E23: 211563 | F23: Kenmare Moma Processing (Mauritius) Limited | G23: 523356 | H23: ST-R.O.A. | I23: Pending | J23: =IFERROR(VLOOKUP(D23, '19.05.2026'!D:J, 7, FALSE), "") -> ACCOUNT - UP TO DATE | K23: SCL-K11 TS-22kW - Item No 28000552 (Qty: 2) | L23: =B23 -> 46199
F24: Total Value (All): | G24: =SUM(G3:G23) -> 3448456.7
F26: BREAKDOWN
F27: Cash Sale (May): | G27: =SUMIFS(G3:G23, J3:J23, "*CASH SALE*", L3:L23, ">="&EOMONTH(TODAY(),-1)+1, L3:L23, "<="&EOMONTH(TODAY(),0)) -> 1640089.6 | I27: Cash Sale (June): | J27: =SUMIFS(G3:G23, J3:J23, "*CASH SALE*", L3:L23, ">="&EOMONTH(TODAY(),0)+1, L3:L23, "<="&EOMONTH(TODAY(),1)) -> 0
F28: Account (May): | G28: =SUMIFS(G3:G23, J3:J23, "*ACCOUNT*", L3:L23, ">="&EOMONTH(TODAY(),-1)+1, L3:L23, "<="&EOMONTH(TODAY(),0)) -> 1285011.1 | I28: Account (June): | J28: =SUMIFS(G3:G23, J3:J23, "*ACCOUNT*", L3:L23, ">="&EOMONTH(TODAY(),0)+1, L3:L23, "<="&EOMONTH(TODAY(),1)) -> 523356
A30: Date | B30: Delivery Date | C30: Job Number | D30: SO Number | E30: Customer Ref. | F30: Customer | G30: Total | H30: Sales Rep | I30: Status | J30: Payment Status | K30: Comments
A31: 46154 | B31: 46162.325 | C31: FM4060 | D31: SO4580 | E31: FM4060 | F31: Roto Tank | G31: 10263.75 | H31: Sizwe Tshabalala | I31: Ready - Dispatch | J31: CASH SALE - PAID | K31: CLIENT TO COLLECT,
A32: 46154 | B32: 46162 | C32: FM4055 | D32: SO4577 | E32: FM4055 | F32: Vincent | G32: 12224.5 | H32: Simon Mokgola | I32: In Progress | J32: CASH SALE - PAID | K32: CLIENT TO COLLECT 20/05/2026
A33: 46142 | B33: 46162.325 | C33: FM4022 | D33: SO4558 | E33: FMTA4398-Thabakgolo | F33: Oribi Air CC | G33: 89230.8 | H33: Mashudu Tshifularo | I33: In Progress | J33: CASH SALE - PAID | K33: PARTIAL DEL - MT 19/05/2026
F34: Due Today - Total: | G34: =SUM(G31:G33) -> 111719.05
F36: Ready-Dispatch: | G36: =SUMIFS(G3:G23, I3:I23, "*Ready*Dispatch*") -> 10263.75

Sheet 21.05.2026
A1: SALES ORDER REPORT | K1: =TODAY() -> 46171
A2: Date | B2: Delivery Date | C2: Job Number | D2: SO Number | E2: Customer Ref. | F2: Customer | G2: Total | H2: Sales Rep | I2: Status | J2: Payment Status | K2: Details | L2: Planned Delivery Date
A3: 46142 | B3: 46163.349 | C3: FM4022 | D3: SO4558 | E3: FMTA4398-Thabakgolo | F3: Oribi Air CC | G3: 89230.8 | H3: MT | I3: In Progress | J3: CASH SALE - PAID | K3: KSB250 5.1.1 (Qty: 8), KSB 315 5.6.1 (Qty: 4) | L3: =B3 -> 46163.349
A4: 46149 | B4: 46163.349 | C4: FM4039 | D4: SO4571 | E4: Cash Sale | F4: Shonisani Rambau Construction | G4: 24910.15 | H4: ST | I4: In Progress | J4: CASH SALE - PAID | K4: UV 630-3-6 c/w 1.5 kW 6 Pole 380 V Motor w/ Bird Screen (Qty: 1) | L4: =B4 -> 46163.349
A5: 46154 | B5: 46163.349 | C5: FM4060 | D5: SO4580 | E5: FM4060 | F5: Roto Tank | G5: 10263.75 | H5: ST | I5: Ready - Dispatch | J5: CASH SALE - PAID | K5: CMP 616 2M (Qty: 1) | L5: =B5 -> 46163.349
A6: 46112 | B6: 46164 | C6: FM4080 | D6: SO4597 | E6: FM4078-4081 - REA VAYA - ROOF LEVEL | F6: TESLA COMMS | G6: 75285.9 | H6: SM | I6: In Progress | J6: CASH SALE - PAID | K6: MAXFLO 630/250/14 A c/w 1,50KW 4P 380V (EAF01 - Admin Roof Level Fan) (Qty: 1), 630 Diam Silencer 1.5D Podded (Qty: 2), 630 Diam Counter Flange (Qty: 2), 630 Diam Mounting Feet (Qty: 4), 630 to 1000 NDB GREEN Neoprene Floor Mounts (Qty: 8), MAXFLO 630/250/14 A c/w 0,75KW 4P 380V (FAF02 - Admin Roof Level Fan) (Qty: 1), 630 Diam Silencer 1.5D Podded (Qty: 2), 630 Diam Counter Flange (Qty: 2), 630 Diam Mounting Feet (Qty: 4), 630 to 1000 NDB GREEN Neoprene Floor Mounts (Qty: 8), LINEO 315 (EAF01 - Admin Mezzanine Fan) (Qty: 1), 315 Diam Tube Silencer 600L (Qty: 2), MAXFLO 315/150/10 A c/w 0,55KW 2P 380V (EAF02 - Admin Mezzanine Fan) (Qty: 1), 315 Diam Silencer 1.5D Podded (Qty: 2), 315 Diam Counter Flange (Qty: 2), 315 Diam Mounting Feet (Qty: 4), 315 to 560 NDA RED ANeoprene Floor Mounts (Qty: 8) | L6: =B6 -> 46164
A7: 46157 | B7: 46164 | C7: FM4076 | D7: SO4594 | E7: PR 033836 | F7: Butec | G7: 21407.04 | H7: MT | I7: In Progress | J7: CASH SALE - C.O.D. | K7: MAXFLO 630/250/14 A c/w 2,20KW 4P 380V (Qty: 1), 630 Diam Melinex Silencer 1.5D Podded (Qty: 1), 630 Diam Melinex Silencer 1.0D Podded (Qty: 1), 630 Diam Counter Flange (Qty: 1), 630 Diam Mounting Feet (Qty: 4), 630 to 1000 NDB GREEN Neoprene Floor Mounts (Qty: 8) | L7: =B7 -> 46164
A8: 46157 | B8: 46164 | C8: FM4075 | D8: SO4593 | E8: PO146488 | F8: Howden Power a Div of Howden Africa (Pty) LTD | G8: 17622.6 | H8: ST | I8: In Progress | J8: ACCOUNT - UP TO DATE | K8: KDAXIS 300 (Qty: 3), 250/355 Wall Cowl Galvanized (Qty: 3), V 150/6 AR (Qty: 1), PIR Sensor (Qty: 1) | L8: =B8 -> 46164
A9: 46160 | B9: 46164 | C9: FM4077 | D9: SO4595 | E9: FM4077 | F9: Duduzani | G9: 21986.85 | H9: SM | I9: In Progress | J9: ACCOUNT - UP TO DATE | K9: MAJAX-3 630 c/w 1,10KW 4P 380V (Qty: 1), 630 Diam Silencer 1.5D Podded (Qty: 2), 630 Diam Counter Flange (Qty: 2), 630 Diam Mounting Feet (Qty: 4), 630 to 1000 NDB GREEN Neoprene Floor Mounts (Qty: 8) | L9: =B9 -> 46164
A10: 46077 | B10: 46169 | C10: FM3874 | D10: SO4404 | E10: PO2174 | F10: ITD North Pty Ltd | G10: 94247.1 | H10: MT | I10: In Progress | J10: CASH SALE – PARTIAL | K10: RDH 710 K2 - Nicotra Fan (Qty: 1) | L10: =B10 -> 46169
A11: 46069 | B11: 46170 | C11: FM3841 | D11: SO4372 | E11: PO2213 | F11: Hucra Fans | G11: 379993.35 | H11: S.A.- HUCRA | I11: In Progress | J11: ACCOUNT - UP TO DATE | K11: SCL K11 MS - 11.0kW - 525V (Qty: 3) | L11: =B11 -> 46170
A12: 46112 | B12: 46170 | C12: FM3974 | D12: SO4502 | E12: 210719 | F12: Kenmare Moma Processing (Mauritius) Limited | G12: 103711 | H12: ST | I12: In Progress | J12: ACCOUNT - UP TO DATE | K12: SCL-K10 MS-11kW - Item no 28000234 (Qty: 1) | L12: =B12 -> 46170
A13: 46112 | B13: 46170 | C13: FM3997 | D13: SO4525 | E13: 211035 | F13: Kenmare Moma Processing (Mauritius) Limited | G13: 83433 | H13: ST | I13: In Progress | J13: ACCOUNT - UP TO DATE | K13: SCL-K08 MS-7.5kW (Qty: 1) | L13: =B13 -> 46170
A14: 46156 | B14: 46171 | C14: FM4070 | D14: SO4588 | E14: ELEIP002400315 -08 | F14: Elroi Trading Enterprise | G14: 234420.6 | H14: SM | I14: In Progress | J14: CASH SALE - PAID | K14: MAXFLO 500/150/10 A c/w 0.37KW 4P 380V 304SS (Qty: 1), 500 Diam Mounting Feet (Qty: 2), SAL 630 (Qty: 1), Majax-2 1250 20.D.8 c/w 18.5kW 4 Pole 380V (Qty: 1), 1250 Diam Silencer 1.5D Podded (Qty: 2), 1250 Diam Counter Flange (Qty: 2), 1250 Diam Mounting Feet (Qty: 4), PD3 RED - Anti Vibration Rubber Mounts (Qty: 8) | L14: =B14 -> 46171
A15: 46111 | B15: 46171 | C15: FM3967 | D15: SO4492 | E15: PO260306 | F15: Alpha Air Ventilation Services | G15: 9014.21 | H15: ST | I15: On Hold | J15: =IFERROR(VLOOKUP(D15, '20.05.2026'!D:J, 7, FALSE), "") -> CASH SALE | K15: MAJAX-2 500 c/w 0,55KW 4P 380V (Qty: 1), 500 Diam Counter Flange (Qty: 2) | L15: =B15 -> 46171
A16: 46111 | B16: 46171 | C16: FM3990 | D16: SO4517 | E16: PO:0000426 | F16: Compu Cool (Pty) Ltd | G16: 169353.6 | H16: MT | I16: On Hold | J16: =IFERROR(VLOOKUP(D16, '20.05.2026'!D:J, 7, FALSE), "") -> ACCOUNT - UP TO DATE | K16: UV710/3/6 (Qty: 6) | L16: =B16 -> 46171
A17: 46128 | B17: 46171 | C17: Pending | D17: SO4554 | E17: FMTA4599 | F17: Matla Solution Group | G17: 82900.05 | H17: MT | I17: Pending | J17: =IFERROR(VLOOKUP(D17, '20.05.2026'!D:J, 7, FALSE), "") -> ACCOUNT - UP TO DATE | K17: LINEO 315 QUIET - EF 1 (Qty: 1), LINEO 250 QUIET - EF 2 (Qty: 1), LINEO 200 QUIET - EF 3 (Qty: 1), KDAXIS 200 - EF 4 (Qty: 1), KDAXIS 200 - EF 5 (Qty: 1), MAXFLO 630/250/14 A c/w 1,10KW 4P 380V - FA 1 (Qty: 1), 630 Diam Silencer 1.5D Podded (Qty: 2), 630 Diam Counter Flange (Qty: 2), 630 Diam Mounting Feet (Qty: 4), 630 to 1000 NDB GREEN Neoprene Floor Mounts (Qty: 8), MAXFLO 710/250/14 A c/w 1,10KW 4P 380V - FA 2 (Qty: 1), 710 Diam Silencer 1.5D Podded (Qty: 2), 710 Diam Counter Flange (Qty: 2), 710 Diam Mounting Feet (Qty: 4), 630 to 1000 NDB GREEN Neoprene Floor Mounts (Qty: 8) | L17: =B17 -> 46171
A18: 46142 | B18: 46171 | C18: Pending | D18: SO4556 | E18: Constitutional Hill | F18: LJ Trading & Projects (Pty) Ltd | G18: 554227.55 | H18: SM | I18: Pending | J18: =IFERROR(VLOOKUP(D18, '20.05.2026'!D:J, 7, FALSE), "") -> CASH SALE | K18: Constitutional Hill (Qty: 1) | L18: =B18 -> 46171
A19: 46142 | B19: 46171 | C19: Pending | D19: SO4553 | E19: FMTA4519 | F19: ST AIR SERVICES AND MAINTENANCE (PTY) LTD | G19: 426010.6 | H19: SM | I19: Pending | J19: =IFERROR(VLOOKUP(D19, '20.05.2026'!D:J, 7, FALSE), "") -> ACCOUNT - UP TO DATE | K19: Mimosa Mall Office Park (Qty: 1) | L19: =B19 -> 46171
A20: 46142 | B20: 46171 | C20: FM4036 | D20: SO4555 | E20: FM4035-FM4036 | F20: Michmat Projects | G20: 310411 | H20: MT - R.O.A | I20: Pending | J20: =IFERROR(VLOOKUP(D20, '20.05.2026'!D:J, 7, FALSE), "") -> CASH SALE | K20: MFAJAX-3 1250 c/w 45,00KW 4P 380V (Qty: 3), 1250 Diam Counter Flange (Qty: 6), 1250 Diam Mounting Feet (Qty: 6), 630 to 1000 NDB GREEN Neoprene Floor Mounts (Qty: 12), MAJAX-3 560 c/w 5,50KW 2P 380V (Qty: 2), 560 Diam Counter Flange (Qty: 4), 560 Diam Mounting Feet (Qty: 4), 315 to 560 NDA RED ANeoprene Floor Mounts (Qty: 8) | L20: =B20 -> 46171
A21: 46142 | B21: 46171 | C21: Pending | D21: SO4557 | E21: nan | F21: Vigeta Pty Ltd | G21: 204447 | H21: SM | I21: Pending | J21: =IFERROR(VLOOKUP(D21, '20.05.2026'!D:J, 7, FALSE), "") -> CASH SALE | K21: 630 Diam Vertical Discharge BASE c/w 2.2kW 4P 380V (Qty: 10) | L21: =B21 -> 46171
A22: 46155 | B22: 46199 | C22: FM4064 | D22: SO4584 | E22: 211563 | F22: Kenmare Moma Processing (Mauritius) Limited | G22: 523356 | H22: ST - R.O.A | I22: Pending | J22: =IFERROR(VLOOKUP(D22, '20.05.2026'!D:J, 7, FALSE), "") -> ACCOUNT - UP TO DATE | K22: SCL-K11 TS-22kW - Item No 28000552 (Qty: 2) | L22: =B22 -> 46199
F23: Total Value (All): | G23: =SUM(G3:G22) -> 3436232.2
F25: BREAKDOWN
F26: Cash Sale (May): | G26: =SUMIFS(G3:G22, J3:J22, "*CASH SALE*", L3:L22, ">="&EOMONTH(TODAY(),-1)+1, L3:L22, "<="&EOMONTH(TODAY(),0)) -> 1627865.1 | I26: Cash Sale (June): | J26: =SUMIFS(G3:G22, J3:J22, "*CASH SALE*", L3:L22, ">="&EOMONTH(TODAY(),0)+1, L3:L22, "<="&EOMONTH(TODAY(),1)) -> 0
F27: Account (May): | G27: =SUMIFS(G3:G22, J3:J22, "*ACCOUNT*", L3:L22, ">="&EOMONTH(TODAY(),-1)+1, L3:L22, "<="&EOMONTH(TODAY(),0)) -> 1285011.1 | I27: Account (June): | J27: =SUMIFS(G3:G22, J3:J22, "*ACCOUNT*", L3:L22, ">="&EOMONTH(TODAY(),0)+1, L3:L22, "<="&EOMONTH(TODAY(),1)) -> 523356
A29: Date | B29: Delivery Date | C29: Job Number | D29: SO Number | E29: Customer Ref. | F29: Customer | G29: Total | H29: Sales Rep | I29: Status | J29: Payment Status | K29: Comments
A30: 46154 | B30: 46163.349 | C30: FM4060 | D30: SO4580 | E30: FM4060 | F30: Roto Tank | G30: 10263.75 | H30: ST | I30: Ready - Dispatch | J30: CASH SALE - PAID | K30: CLIENT TO COLLECT, WHEN AVAILABLE
A31: 46142 | B31: 46163.349 | C31: FM4022 | D31: SO4558 | E31: FMTA4398-Thabakgolo | F31: Oribi Air CC | G31: 89230.8 | H31: MT | I31: In Progress | J31: CASH SALE - PAID | K31: PARTIAL DEL - MT 19/05/2026
A32: 46149 | B32: 46163.349 | C32: FM4039 | D32: SO4571 | E32: Cash Sale | F32: Shonisani Rambau Construction | G32: 24910.15 | H32: ST | I32: In Progress | J32: CASH SALE - PAID
F33: Due Today - Total: | G33: =SUM(G30:G32) -> 124404.7
F35: Ready-Dispatch: | G35: =SUMIFS(G3:G22, I3:I22, "*Ready*Dispatch*") -> 10263.75

Sheet 25.05.2026
A1: SALES ORDER REPORT | K1: =TODAY() -> 46171
A2: Date | B2: Delivery Date | C2: Job Number | D2: SO Number | E2: Customer Ref. | F2: Customer | G2: Total | H2: Sales Rep | I2: Status | J2: Payment Status | K2: Details | L2: Planned Delivery Date
A3: 46149 | B3: 46167.579 | C3: FM4039 | D3: SO4571 | E3: Cash Sale | F3: Shonisani Rambau Construction | G3: 24910.15 | H3: ST | I3: In Progress | J3: CASH SALE - PAID | K3: UV 630-3-6 c/w 1.5 kW 6 Pole 380 V Motor w/ Bird Screen (Qty: 1) | L3: =B3 -> 46167.579
A4: 46154 | B4: 46167.579 | C4: FM4060 | D4: SO4580 | E4: FM4060 | F4: Roto Tank | G4: 10263.75 | H4: ST | I4: Ready - Dispatch | J4: CASH SALE - PAID | K4: CMP 616 2M (Qty: 1) | L4: =B4 -> 46167.579
A5: 46077 | B5: 46169 | C5: FM3874 | D5: SO4404 | E5: PO2174 | F5: ITD North Pty Ltd | G5: 94247.1 | H5: MT | I5: In Progress | J5: CASH SALE – PARTIAL | K5: RDH 710 K2 - Nicotra Fan (Qty: 1) | L5: =B5 -> 46169
A6: 46069 | B6: 46170 | C6: FM3841 | D6: SO4372 | E6: PO2213 | F6: Hucra Fans | G6: 379993.35 | H6: SAHF | I6: In Progress | J6: ACCOUNT - UP TO DATE | K6: SCL K11 MS - 11.0kW - 525V (Qty: 3) | L6: =B6 -> 46170
A7: 46112 | B7: 46170 | C7: FM3974 | D7: SO4502 | E7: 210719 | F7: Kenmare Moma Processing (Mauritius) Limited | G7: 103711 | H7: ST | I7: In Progress | J7: ACCOUNT - UP TO DATE | K7: SCL-K10 MS-11kW - Item no 28000234 (Qty: 1) | L7: =B7 -> 46170
A8: 46112 | B8: 46170 | C8: FM3997 | D8: SO4525 | E8: 211035 | F8: Kenmare Moma Processing (Mauritius) Limited | G8: 83433 | H8: ST | I8: In Progress | J8: ACCOUNT - UP TO DATE | K8: SCL-K08 MS-7.5kW (Qty: 1) | L8: =B8 -> 46170
A9: 46156 | B9: 46171 | C9: FM4070 | D9: SO4588 | E9: ELEIP002400315 -08 | F9: Elroi Trading Enterprise | G9: 234420.6 | H9: SM | I9: In Progress | J9: CASH SALE - PAID | K9: MAXFLO 500/150/10 A c/w 0.37KW 4P 380V 304SS (Qty: 1), 500 Diam Mounting Feet (Qty: 2), SAL 630 (Qty: 1), Majax-2 1250 20.D.8 c/w 18.5kW 4 Pole 380V (Qty: 1), 1250 Diam Silencer 1.5D Podded (Qty: 2), 1250 Diam Counter Flange (Qty: 2), 1250 Diam Mounting Feet (Qty: 4), PD3 RED - Anti Vibration Rubber Mounts (Qty: 8) | L9: =B9 -> 46171
A10: 46111 | B10: 46171 | C10: FM3967 | D10: SO4492 | E10: PO260306 | F10: Alpha Air Ventilation Services | G10: 9014.21 | H10: ST | I10: On Hold | J10: =IFERROR(VLOOKUP(D10, '21.05.2026'!D:J, 7, FALSE), "") -> CASH SALE | K10: MAJAX-2 500 c/w 0,55KW 4P 380V (Qty: 1), 500 Diam Counter Flange (Qty: 2) | L10: =B10 -> 46171
A11: 46111 | B11: 46171 | C11: FM3990 | D11: SO4517 | E11: PO:0000426 | F11: Compu Cool (Pty) Ltd | G11: 169353.6 | H11: MT | I11: On Hold | J11: =IFERROR(VLOOKUP(D11, '21.05.2026'!D:J, 7, FALSE), "") -> ACCOUNT - UP TO DATE | K11: UV710/3/6 (Qty: 6) | L11: =B11 -> 46171
A12: 46128 | B12: 46171 | C12: Pending | D12: SO4554 | E12: FMTA4599 | F12: Matla Solution Group | G12: 82900.05 | H12: MT | I12: Pending | J12: =IFERROR(VLOOKUP(D12, '21.05.2026'!D:J, 7, FALSE), "") -> ACCOUNT - UP TO DATE | K12: LINEO 315 QUIET - EF 1 (Qty: 1), LINEO 250 QUIET - EF 2 (Qty: 1), LINEO 200 QUIET - EF 3 (Qty: 1), KDAXIS 200 - EF 4 (Qty: 1), KDAXIS 200 - EF 5 (Qty: 1), MAXFLO 630/250/14 A c/w 1,10KW 4P 380V - FA 1 (Qty: 1), 630 Diam Silencer 1.5D Podded (Qty: 2), 630 Diam Counter Flange (Qty: 2), 630 Diam Mounting Feet (Qty: 4), 630 to 1000 NDB GREEN Neoprene Floor Mounts (Qty: 8), MAXFLO 710/250/14 A c/w 1,10KW 4P 380V - FA 2 (Qty: 1), 710 Diam Silencer 1.5D Podded (Qty: 2), 710 Diam Counter Flange (Qty: 2), 710 Diam Mounting Feet (Qty: 4), 630 to 1000 NDB GREEN Neoprene Floor Mounts (Qty: 8) | L12: =B12 -> 46171
A13: 46142 | B13: 46171 | C13: Pending | D13: SO4556 | E13: Constitutional Hill | F13: LJ Trading & Projects (Pty) Ltd | G13: 554227.55 | H13: SM | I13: Pending | J13: =IFERROR(VLOOKUP(D13, '21.05.2026'!D:J, 7, FALSE), "") -> CASH SALE | K13: Constitutional Hill (Qty: 1) | L13: =B13 -> 46171
A14: 46142 | B14: 46171 | C14: Pending | D14: SO4553 | E14: FMTA4519 | F14: ST AIR SERVICES AND MAINTENANCE (PTY) LTD | G14: 426010.6 | H14: SM | I14: Pending | J14: =IFERROR(VLOOKUP(D14, '21.05.2026'!D:J, 7, FALSE), "") -> ACCOUNT - UP TO DATE | K14: Mimosa Mall Office Park (Qty: 1) | L14: =B14 -> 46171
A15: 46142 | B15: 46171 | C15: FM4036 | D15: SO4555 | E15: FM4035-FM4036 | F15: Michmat Projects | G15: 310411 | H15: M-R | I15: Pending | J15: =IFERROR(VLOOKUP(D15, '21.05.2026'!D:J, 7, FALSE), "") -> CASH SALE | K15: MFAJAX-3 1250 c/w 45,00KW 4P 380V (Qty: 3), 1250 Diam Counter Flange (Qty: 6), 1250 Diam Mounting Feet (Qty: 6), 630 to 1000 NDB GREEN Neoprene Floor Mounts (Qty: 12), MAJAX-3 560 c/w 5,50KW 2P 380V (Qty: 2), 560 Diam Counter Flange (Qty: 4), 560 Diam Mounting Feet (Qty: 4), 315 to 560 NDA RED ANeoprene Floor Mounts (Qty: 8) | L15: =B15 -> 46171
A16: 46142 | B16: 46171 | C16: Pending | D16: SO4557 | E16: nan | F16: Vigeta Pty Ltd | G16: 204447 | H16: SM | I16: Pending | J16: =IFERROR(VLOOKUP(D16, '21.05.2026'!D:J, 7, FALSE), "") -> CASH SALE | K16: 630 Diam Vertical Discharge BASE c/w 2.2kW 4P 380V (Qty: 10) | L16: =B16 -> 46171
A17: 46164 | B17: 46173 | C17: FM4092 | D17: SO4610 | E17: FM4092 | F17: Gibela Trade and Invest 1247 CC t/a GTI AIR | G17: 16610.6 | H17: SM | I17: In Progress | J17: CASH SALE - PAID | K17: Spare Impeller (Qty: 2), 630 Diam Silencer 1.5D Podded (Qty: 2) | L17: =B17 -> 46173
A18: 46155 | B18: 46199 | C18: FM4064 | D18: SO4584 | E18: 211563 | F18: Kenmare Moma Processing (Mauritius) Limited | G18: 523356 | H18: S-R | I18: In Progress | J18: ACCOUNT - UP TO DATE | K18: SCL-K11 TS-22kW - Item No 28000552 (Qty: 2) | L18: =B18 -> 46199
F19: Total Value (All): | G19: =SUMIF(I3:I18,"<>Pending",G3:G18) -> 1649313.4
F21: BREAKDOWN
F22: Cash Sale (May): | G22: =SUMIFS(G3:G18, J3:J18, "*CASH SALE*", L3:L18, ">="&EOMONTH(TODAY(),-1)+1, L3:L18, "<="&EOMONTH(TODAY(),0), I3:I18, "<>Pending") -> 389466.41 | I22: Cash Sale (June): | J22: =SUMIFS(G3:G18, J3:J18, "*CASH SALE*", L3:L18, ">="&EOMONTH(TODAY(),0)+1, L3:L18, "<="&EOMONTH(TODAY(),1), I3:I18, "<>Pending") -> 0
F23: Account (May): | G23: =SUMIFS(G3:G18, J3:J18, "*ACCOUNT*", L3:L18, ">="&EOMONTH(TODAY(),-1)+1, L3:L18, "<="&EOMONTH(TODAY(),0), I3:I18, "<>Pending") -> 736490.95 | I23: Account (June): | J23: =SUMIFS(G3:G18, J3:J18, "*ACCOUNT*", L3:L18, ">="&EOMONTH(TODAY(),0)+1, L3:L18, "<="&EOMONTH(TODAY(),1), I3:I18, "<>Pending") -> 523356
A25: Date | B25: Delivery Date | C25: Job Number | D25: SO Number | E25: Customer Ref. | F25: Customer | G25: Total | H25: Sales Rep | I25: Status | J25: Payment Status | K25: Comments
A26: 46149 | B26: 46167.579 | C26: FM4039 | D26: SO4571 | E26: Cash Sale | F26: Shonisani Rambau Construction | G26: 24910.15 | H26: ST | I26: In Progress | J26: CASH SALE - PAID
A27: 46154 | B27: 46167.579 | C27: FM4060 | D27: SO4580 | E27: FM4060 | F27: Roto Tank | G27: 10263.75 | H27: ST | I27: Ready - Dispatch | J27: CASH SALE - PAID | K27: CLIENT TO COLLECT, WHEN AVAILABLE
F28: Due Today - Total: | G28: =SUM(G26:G27) -> 35173.9
F30: Ready-Dispatch: | G30: =SUMIFS(G3:G18, I3:I18, "*Ready*Dispatch*") -> 10263.75
A33: Recommended Print Range: A1:L37
A34: Suggested Date for Next Update: 14.02.2026

Sheet 28.05.2026
A1: SALES ORDER REPORT | K1: =TODAY() -> 46171
A2: Date | B2: Delivery Date | C2: Job Number | D2: SO Number | E2: Customer Ref. | F2: Customer | G2: Total | H2: Sales Rep | I2: Status | J2: Payment Status | K2: Details | L2: Planned Delivery Date
A3: 46112 | B3: 46170.559 | C3: FM3974 | D3: SO4502 | E3: 210719 | F3: Kenmare Moma Processing (Mauritius) Limited | G3: 103711 | H3: ST | I3: In Progress | J3: ACCOUNT - UP TO DATE | K3: SCL-K10 MS-11kW - Item no 28000234 (Qty: 1) | L3: =B3 -> 46170.559
A4: 46149 | B4: 46170.559 | C4: FM4039 | D4: SO4571 | E4: Cash Sale | F4: Shonisani Rambau Construction | G4: 24910.15 | H4: ST | I4: In Progress | J4: CASH SALE - PAID | K4: UV 630-3-6 c/w 1.5 kW 6 Pole 380 V Motor w/ Bird Screen (Qty: 1) | L4: =B4 -> 46170.559
A5: 46142 | B5: 46170.559 | C5: Pending | D5: SO4556 | E5: Constitutional Hill | F5: LJ Trading & Projects (Pty) Ltd | G5: 554227.55 | H5: SM | I5: Pending | K5: Constitutional Hill (Qty: 1) | L5: =B5 -> 46170.559
A6: 46156 | B6: 46171 | C6: FM4070 | D6: SO4588 | E6: ELEIP002400315 -08 | F6: Elroi Trading Enterprise | G6: 234420.6 | H6: SM | I6: In Progress | J6: CASH SALE - PAID | K6: MAXFLO 500/150/10 A c/w 0.37KW 4P 380V 304SS (Qty: 1), 500 Diam Mounting Feet (Qty: 2), SAL 630 (Qty: 1), Majax-2 1250 20.D.8 c/w 18.5kW 4 Pole 380V (Qty: 1), 1250 Diam Silencer 1.5D Podded (Qty: 2), 1250 Diam Counter Flange (Qty: 2), 1250 Diam Mounting Feet (Qty: 4), PD3 RED - Anti Vibration Rubber Mounts (Qty: 8) | L6: =B6 -> 46171
A7: 46111 | B7: 46171 | C7: FM3967 | D7: SO4492 | E7: PO260306 | F7: Alpha Air Ventilation Services | G7: 9014.21 | H7: ST | I7: On Hold | K7: MAJAX-2 500 c/w 0,55KW 4P 380V (Qty: 1), 500 Diam Counter Flange (Qty: 2) | L7: =B7 -> 46171
A8: 46111 | B8: 46171 | C8: FM3990 | D8: SO4517 | E8: PO:0000426 | F8: Compu Cool (Pty) Ltd | G8: 169353.6 | H8: MT | I8: On Hold | K8: UV710/3/6 (Qty: 6) | L8: =B8 -> 46171
A9: 46128 | B9: 46171 | C9: Pending | D9: SO4554 | E9: FMTA4599 | F9: Matla Solution Group | G9: 82900.05 | H9: MT | I9: Pending | K9: LINEO 315 QUIET - EF 1 (Qty: 1), LINEO 250 QUIET - EF 2 (Qty: 1), LINEO 200 QUIET - EF 3 (Qty: 1), KDAXIS 200 - EF 4 (Qty: 1), KDAXIS 200 - EF 5 (Qty: 1), MAXFLO 630/250/14 A c/w 1,10KW 4P 380V - FA 1 (Qty: 1), 630 Diam Silencer 1.5D Podded (Qty: 2), 630 Diam Counter Flange (Qty: 2), 630 Diam Mounting Feet (Qty: 4), 630 to 1000 NDB GREEN Neoprene Floor Mounts (Qty: 8), MAXFLO 710/250/14 A c/w 1,10KW 4P 380V - FA 2 (Qty: 1), 710 Diam Silencer 1.5D Podded (Qty: 2), 710 Diam Counter Flange (Qty: 2), 710 Diam Mounting Feet (Qty: 4), 630 to 1000 NDB GREEN Neoprene Floor Mounts (Qty: 8) | L9: =B9 -> 46171
A10: 46142 | B10: 46171 | C10: Pending | D10: SO4553 | E10: FMTA4519 | F10: ST AIR SERVICES AND MAINTENANCE (PTY) LTD | G10: 426010.6 | H10: SM | I10: Pending | K10: Mimosa Mall Office Park (Qty: 1) | L10: =B10 -> 46171
A11: 46142 | B11: 46171 | C11: FM4036 | D11: SO4555 | E11: FM4035-FM4036 | F11: Michmat Projects | G11: 310411 | H11: M-R | I11: Pending | K11: MFAJAX-3 1250 c/w 45,00KW 4P 380V (Qty: 3), 1250 Diam Counter Flange (Qty: 6), 1250 Diam Mounting Feet (Qty: 6), 630 to 1000 NDB GREEN Neoprene Floor Mounts (Qty: 12), MAJAX-3 560 c/w 5,50KW 2P 380V (Qty: 2), 560 Diam Counter Flange (Qty: 4), 560 Diam Mounting Feet (Qty: 4), 315 to 560 NDA RED ANeoprene Floor Mounts (Qty: 8) | L11: =B11 -> 46171
A12: 46142 | B12: 46171 | C12: Pending | D12: SO4557 | E12: nan | F12: Vigeta Pty Ltd | G12: 204447 | H12: SM | I12: Pending | K12: 630 Diam Vertical Discharge BASE c/w 2.2kW 4P 380V (Qty: 10) | L12: =B12 -> 46171
A13: 46169 | B13: 46173 | C13: Pending | D13: SO4618 | E13: P.O. NO. 11623 | F13: Brasco Group | G13: 8856.15 | H13: SM | I13: Pending | L13: =B13 -> 46173
A14: 46167 | B14: 46195 | C14: FM4098 | D14: SO4614 | E14: 14352 | F14: Arta Masjinerie | G14: 73266.5 | H14: SM | I14: In Progress | J14: ACCOUNT - UP TO DATE | K14: Majax-3 800 c/w 3kw 4P 380V (Qty: 5.0) | L14: =B14 -> 46195
A15: 46155 | B15: 46199 | C15: FM4064 | D15: SO4584 | E15: 211563 | F15: Kenmare Moma Processing (Mauritius) Limited | G15: 523356 | H15: S-R | I15: In Progress | J15: ACCOUNT - UP TO DATE | K15: SCL-K11 TS-22kW - Item No 28000552 (Qty: 2) | L15: =B15 -> 46199
A16: 46167 | B16: 46203 | C16: FM4097 | D16: SO4613 | E16: PO146777 | F16: Howden Power a Div of Howden Africa (Pty) LTD | G16: 220505.6 | H16: ST | I16: In Progress | J16: ACCOUNT - UP TO DATE | K16: Fumax 1000 c/w 22kW 4Pole (Qty: 2.0) | L16: =B16 -> 46203
A17: 46167 | B17: 46203 | C17: FM4099 | D17: SO4615 | E17: 62423 | F17: Chabo & Joubert Air Conditioning (Pty) Ltd | G17: 25694.45 | H17: ST | I17: In Progress | J17: ACCOUNT - UP TO DATE | K17: K-TEX 50-30-4 (Qty: 1.0) | L17: =B17 -> 46203
A18: 46170 | B18: 46203 | C18: Pending | D18: SO4621 | E18: LT69511 | F18: Luft Technik (Pty) Ltd | G18: 1860403 | H18: MT | I18: Pending | L18: =B18 -> 46203
F19: Total Value (All): | G19: =SUMIF(I3:I18,"<>Pending",G3:G18) -> 1384232.1
F21: BREAKDOWN
F22: Cash Sale (May): | G22: =SUMIFS(G3:G18, J3:J18, "*CASH SALE*", L3:L18, ">="&EOMONTH(TODAY(),-1)+1, L3:L18, "<="&EOMONTH(TODAY(),0), I3:I18, "<>Pending") -> 259330.75 | I22: Cash Sale (June): | J22: =SUMIFS(G3:G18, J3:J18, "*CASH SALE*", L3:L18, ">="&EOMONTH(TODAY(),0)+1, L3:L18, "<="&EOMONTH(TODAY(),1), I3:I18, "<>Pending") -> 0
F23: Account (May): | G23: =SUMIFS(G3:G18, J3:J18, "*ACCOUNT*", L3:L18, ">="&EOMONTH(TODAY(),-1)+1, L3:L18, "<="&EOMONTH(TODAY(),0), I3:I18, "<>Pending") -> 103711 | I23: Account (June): | J23: =SUMIFS(G3:G18, J3:J18, "*ACCOUNT*", L3:L18, ">="&EOMONTH(TODAY(),0)+1, L3:L18, "<="&EOMONTH(TODAY(),1), I3:I18, "<>Pending") -> 842822.55
A26: Date | B26: Delivery Date | C26: Job Number | D26: SO Number | E26: Customer Ref. | F26: Customer | G26: Total | H26: Sales Rep | I26: Status | J26: Payment Status | K26: Comments
A27: 46112 | B27: 46170.559 | C27: FM3974 | D27: SO4502 | E27: 210719 | F27: Kenmare Moma Processing (Mauritius) Limited | G27: 103711 | H27: ST | I27: In Progress | J27: ACCOUNT - UP TO DATE
A28: 46149 | B28: 46170.559 | C28: FM4039 | D28: SO4571 | E28: Cash Sale | F28: Shonisani Rambau Construction | G28: 24910.15 | H28: ST | I28: In Progress | J28: CASH SALE - PAID
A29: 46142 | B29: 46170.559 | C29: Pending | D29: SO4556 | E29: Constitutional Hill | F29: LJ Trading & Projects (Pty) Ltd | G29: 554227.55 | H29: SM | I29: Pending
F30: Due Today - Total: | G30: =SUM(G27:G29) -> 682848.7
F32: Ready-Dispatch: | G32: =SUMIFS(G3:G18, I3:I18, "*Ready*Dispatch*") -> 0

Sheet 29.05.2026
A1: SALES ORDER REPORT | K1: =TODAY() -> 46171
A2: Date | B2: Delivery Date | C2: Job Number | D2: SO Number | E2: Customer Ref. | F2: Customer | G2: Total | H2: Sales Rep | I2: Status | J2: Payment Status | K2: Details | L2: Planned Delivery Date
A3: 46149 | B3: 46171.422 | C3: FM4039 | D3: SO4571 | E3: Cash Sale | F3: Shonisani Rambau Construction | G3: 24910.15 | H3: ST | I3: In Progress | J3: CASH SALE - PAID | K3: UV 630-3-6 c/w 1.5 kW 6 Pole 380 V Motor w/ Bird Screen (Qty: 1) | L3: =B3 -> 46171.422
A4: 46171 | B4: 46171.422 | C4: FM4106 | D4: SO4622 | E4: PO2267 | F4: Hucra Fans | G4: 10361.5 | H4: SAHF | I4: In Progress | J4: ACCOUNT - UP TO DATE | K4: CMA-324-2T (Qty: 1) | L4: =B4 -> 46171.422
A5: 46171 | B5: 46171.422 | C5: FM4076 | D5: SO4625 | E5: PO-000008707 | F5: Butec | G5: 5023.2 | H5: MT | I5: In Progress | J5: CASH SALE - C.OD. | K5: 630 Diam Counter Flange (Qty: 3), 630 Diam Flexible Connection (Qty: 3) | L5: =B5 -> 46171.422
A6: 46156 | B6: 46174 | C6: FM4070 | D6: SO4588 | E6: ELEIP002400315 -08 | F6: Elroi Trading Enterprise | G6: 234420.6 | H6: SM | I6: In Progress | J6: CASH SALE - PAID | K6: MAXFLO 500/150/10 A c/w 0.37KW 4P 380V 304SS (Qty: 1), 500 Diam Mounting Feet (Qty: 2), SAL 630 (Qty: 1), Majax-2 1250 20.D.8 c/w 18.5kW 4 Pole 380V (Qty: 1), 1250 Diam Silencer 1.5D Podded (Qty: 2), 1250 Diam Counter Flange (Qty: 2), 1250 Diam Mounting Feet (Qty: 4), PD3 RED - Anti Vibration Rubber Mounts (Qty: 8) | L6: =B6 -> 46174
A7: 46169 | B7: 46175 | C7: FM4100 | D7: SO4618 | E7: P.O. NO. 11623 | F7: Brasco Group | G7: 8856.15 | H7: SM | I7: In Progress | J7: CASH SALE - PAID | K7: MAJAX-3 500 c/w 1,50KW 2P 380V - (OPTION) (Qty: 1) | L7: =B7 -> 46175
A8: 46167 | B8: 46195 | C8: FM4098 | D8: SO4614 | E8: 14352 | F8: Arta Masjinerie | G8: 73266.5 | H8: SM | I8: In Progress | J8: ACCOUNT - UP TO DATE | K8: Majax-3 800 c/w 3kw 4P 380V (Qty: 5.0) | L8: =B8 -> 46195
A9: 46112 | B9: 46199 | C9: FM3974 | D9: SO4502 | E9: 210719 | F9: Kenmare Moma Processing (Mauritius) Limited | G9: 103711 | H9: ST | I9: In Progress | J9: ACCOUNT - UP TO DATE | K9: SCL-K10 MS-11kW - Item no 28000234 (Qty: 1) | L9: =B9 -> 46199
A10: 46155 | B10: 46199 | C10: FM4064 | D10: SO4584 | E10: 211563 | F10: Kenmare Moma Processing (Mauritius) Limited | G10: 523356 | H10: S-R | I10: In Progress | J10: ACCOUNT - UP TO DATE | K10: SCL-K11 TS-22kW - Item No 28000552 (Qty: 2) | L10: =B10 -> 46199
A11: 46167 | B11: 46203 | C11: FM4097 | D11: SO4613 | E11: PO146777 | F11: Howden Power a Div of Howden Africa (Pty) LTD | G11: 220505.6 | H11: ST | I11: In Progress | J11: ACCOUNT - UP TO DATE | K11: Fumax 1000 c/w 22kW 4Pole (Qty: 2.0) | L11: =B11 -> 46203
A12: 46167 | B12: 46203 | C12: FM4099 | D12: SO4615 | E12: 62423 | F12: Chabo & Joubert Air Conditioning (Pty) Ltd | G12: 25694.45 | H12: ST | I12: In Progress | J12: ACCOUNT - UP TO DATE | K12: K-TEX 50-30-4 (Qty: 1.0) | L12: =B12 -> 46203
A13: 46171 | B13: 46203 | C13: FM4107 | D13: SO4623 | E13: PO:01003747 | F13: Cabmed PTY LTD | G13: 13562.64 | H13: MT | I13: In Progress | J13: ACCOUNT - UP TO DATE | K13: SCL 06R MS - 0.20KW 220V (Qty: 1) | L13: =B13 -> 46203
A14: 46111 | B14: 46203 | C14: FM3967 | D14: SO4492 | E14: PO260306 | F14: Alpha Air Ventilation Services | G14: 9014.21 | H14: ST | I14: On Hold | J14: CASH SALE | K14: MAJAX-2 500 c/w 0,55KW 4P 380V (Qty: 1), 500 Diam Counter Flange (Qty: 2) | L14: =B14 -> 46203
A15: 46111 | B15: 46203 | C15: FM3990 | D15: SO4517 | E15: PO:0000426 | F15: Compu Cool (Pty) Ltd | G15: 169353.6 | H15: MT | I15: On Hold | J15: ACCOUNT - UP TO DATE | K15: UV710/3/6 (Qty: 6) | L15: =B15 -> 46203
A16: 46128 | B16: 46203 | C16: Pending | D16: SO4554 | E16: FMTA4599 | F16: Matla Solution Group | G16: 82900.05 | H16: MT | I16: Pending | K16: LINEO 315 QUIET - EF 1 (Qty: 1), LINEO 250 QUIET - EF 2 (Qty: 1), LINEO 200 QUIET - EF 3 (Qty: 1), KDAXIS 200 - EF 4 (Qty: 1), KDAXIS 200 - EF 5 (Qty: 1), MAXFLO 630/250/14 A c/w 1,10KW 4P 380V - FA 1 (Qty: 1), 630 Diam Silencer 1.5D Podded (Qty: 2), 630 Diam Counter Flange (Qty: 2), 630 Diam Mounting Feet (Qty: 4), 630 to 1000 NDB GREEN Neoprene Floor Mounts (Qty: 8), MAXFLO 710/250/14 A c/w 1,10KW 4P 380V - FA 2 (Qty: 1), 710 Diam Silencer 1.5D Podded (Qty: 2), 710 Diam Counter Flange (Qty: 2), 710 Diam Mounting Feet (Qty: 4), 630 to 1000 NDB GREEN Neoprene Floor Mounts (Qty: 8) | L16: =B16 -> 46203
A17: 46142 | B17: 46203 | C17: Pending | D17: SO4553 | E17: FMTA4519 | F17: ST AIR SERVICES AND MAINTENANCE (PTY) LTD | G17: 426010.6 | H17: SM | I17: Pending | K17: Mimosa Mall Office Park (Qty: 1) | L17: =B17 -> 46203
A18: 46142 | B18: 46203 | C18: FM4036 | D18: SO4555 | E18: FM4035-FM4036 | F18: Michmat Projects | G18: 310411 | H18: M-R | I18: Pending | K18: MFAJAX-3 1250 c/w 45,00KW 4P 380V (Qty: 3), 1250 Diam Counter Flange (Qty: 6), 1250 Diam Mounting Feet (Qty: 6), 630 to 1000 NDB GREEN Neoprene Floor Mounts (Qty: 12), MAJAX-3 560 c/w 5,50KW 2P 380V (Qty: 2), 560 Diam Counter Flange (Qty: 4), 560 Diam Mounting Feet (Qty: 4), 315 to 560 NDA RED ANeoprene Floor Mounts (Qty: 8) | L18: =B18 -> 46203
A19: 46142 | B19: 46203 | C19: Pending | D19: SO4556 | E19: POE12858 | F19: LJ Trading & Projects (Pty) Ltd | G19: 251413.01 | H19: SM | I19: Pending | K19: Constitutional Hill (Qty: 1) | L19: =B19 -> 46203
A20: 46142 | B20: 46203 | C20: Pending | D20: SO4557 | E20: nan | F20: Vigeta Pty Ltd | G20: 204447 | H20: SM | I20: Pending | K20: 630 Diam Vertical Discharge BASE c/w 2.2kW 4P 380V (Qty: 10) | L20: =B20 -> 46203
A21: 46170 | B21: 46203 | C21: Pending | D21: SO4621 | E21: LT69511 | F21: Luft Technik (Pty) Ltd | G21: 1860403 | H21: MT | I21: Pending | K21: LCH HOSPITAL (Qty: 1) | L21: =B21 -> 46203
A22: 46171 | B22: 46203 | C22: FM4108 | D22: SO4624 | E22: PO:030544 | F22: Atlas Air Conditioning (Pty) Ltd | G22: 18400 | H22: MT | I22: Pending | K22: DDMP 10/10 230V (Qty: 1) | L22: =B22 -> 46203
F23: Total Value (All): | G23: =SUMIF(I3:I22,"<>Pending",G3:G22) -> 1422035.6
F25: BREAKDOWN
F26: Cash Sale (May): | G26: =SUMIFS(G3:G22, J3:J22, "*CASH SALE*", L3:L22, ">="&EOMONTH(TODAY(),-1)+1, L3:L22, "<="&EOMONTH(TODAY(),0), I3:I22, "<>Pending") -> 29933.35 | I26: Cash Sale (June): | J26: =SUMIFS(G3:G22, J3:J22, "*CASH SALE*", L3:L22, ">="&EOMONTH(TODAY(),0)+1, L3:L22, "<="&EOMONTH(TODAY(),1), I3:I22, "<>Pending") -> 252290.96
F27: Account (May): | G27: =SUMIFS(G3:G22, J3:J22, "*ACCOUNT*", L3:L22, ">="&EOMONTH(TODAY(),-1)+1, L3:L22, "<="&EOMONTH(TODAY(),0), I3:I22, "<>Pending") -> 10361.5 | I27: Account (June): | J27: =SUMIFS(G3:G22, J3:J22, "*ACCOUNT*", L3:L22, ">="&EOMONTH(TODAY(),0)+1, L3:L22, "<="&EOMONTH(TODAY(),1), I3:I22, "<>Pending") -> 1129449.8
A29: Date | B29: Delivery Date | C29: Job Number | D29: SO Number | E29: Customer Ref. | F29: Customer | G29: Total | H29: Sales Rep | I29: Status | J29: Payment Status | K29: Comments
A30: 46171 | B30: 46171.422 | C30: FM4106 | D30: SO4622 | E30: PO2267 | F30: Hucra Fans | G30: 10361.5 | H30: SAHF | I30: In Progress | J30: ACCOUNT - UP TO DATE
A31: 46149 | B31: 46171.422 | C31: FM4039 | D31: SO4571 | E31: Cash Sale | F31: Shonisani Rambau Construction | G31: 24910.15 | H31: ST | I31: Ready - Dispatch | J31: CASH SALE - PAID
A32: 46171 | B32: 46171.422 | C32: FM4076 | D32: SO4625 | E32: PO-000008707 | F32: Butec | G32: 5023.2 | H32: MT | I32: In Progress | J32: CASH SALE - C.OD.
F33: Due Today - Total: | G33: =SUM(G30:G32) -> 40294.85
F35: Ready-Dispatch: | G35: =SUMIFS(G3:G22, I3:I22, "*Ready*Dispatch*") -> 0
A36: Recommended Print Range: A1:L50
A37: Suggested Date for Next Update: 28.03.2026
